Workbook
Name NombreNegocio: 'AJUSTES'!$C$7
Name RucNegocio: 'AJUSTES'!$C$8
Name TelNegocio: 'AJUSTES'!$C$9
Name DirNegocio: 'AJUSTES'!$C$10
Name Moneda: 'AJUSTES'!$C$11
Name AnioCtl: 'AJUSTES'!$C$12
Name Validez: 'AJUSTES'!$C$13
Name Decimales: 'AJUSTES'!$C$14
Name TasaGeneral: 'AJUSTES'!$C$17
Name TasaReducida: 'AJUSTES'!$C$18

Sheet PRESUPUESTO
B1: MIX SHOP DIGITAL | D1: PRESUPUESTO
B2: Herramientas inteligentes que simplifican tu vida. | D2: Armalo, imprimilo o guardalo en PDF
C4: Completá las celdas amarillas. Los totales y el IVA se calculan solos. Para imprimir: Archivo > Imprimir.
B5: Recibo → | D5: Historial | F5: Panel
B6: Ajustes | D6: Ayuda
B8: =UPPER(NombreNegocio)
B9: =IF(RucNegocio="","","RUC/C.I.: "&RucNegocio&" ")&IF(TelNegocio="","","Tel.: "&TelNegocio&" ")&DirNegocio | P9: =IF($G$14="10 %",TasaGeneral,IF($G$14="5 %",TasaReducida,0))
P10: =IF(LEFT($D$15,2)="Ya",1,0)
B11: Presupuesto N° | F11: Fecha | P11: =SUM(G18:G29)
B12: Cliente
B13: RUC / C.I. del cliente | F13: Teléfono
B14: Válido hasta | D14: =IF(N(G11)=0,"",G11+Validez) | F14: IVA | G14: 10 %
B15: Los precios que escribo… | D15: Ya incluyen el IVA
B17: N° | C17: Descripción | D17: Cant. | E17: Precio unitario | F17: Desc. % | G17: Importe
B18: =IF(C18<>"",1,"") | G18: =IF(N(E18)=0,"",ROUND(IF(N(D18)>0,D18,1)*E18*(1-N(F18)),Decimales))
B19: =IF(C19<>"",2,"") | G19: =IF(N(E19)=0,"",ROUND(IF(N(D19)>0,D19,1)*E19*(1-N(F19)),Decimales))
B20: =IF(C20<>"",3,"") | G20: =IF(N(E20)=0,"",ROUND(IF(N(D20)>0,D20,1)*E20*(1-N(F20)),Decimales))
B21: =IF(C21<>"",4,"") | G21: =IF(N(E21)=0,"",ROUND(IF(N(D21)>0,D21,1)*E21*(1-N(F21)),Decimales))
B22: =IF(C22<>"",5,"") | G22: =IF(N(E22)=0,"",ROUND(IF(N(D22)>0,D22,1)*E22*(1-N(F22)),Decimales))
B23: =IF(C23<>"",6,"") | G23: =IF(N(E23)=0,"",ROUND(IF(N(D23)>0,D23,1)*E23*(1-N(F23)),Decimales))
B24: =IF(C24<>"",7,"") | G24: =IF(N(E24)=0,"",ROUND(IF(N(D24)>0,D24,1)*E24*(1-N(F24)),Decimales))
B25: =IF(C25<>"",8,"") | G25: =IF(N(E25)=0,"",ROUND(IF(N(D25)>0,D25,1)*E25*(1-N(F25)),Decimales))
B26: =IF(C26<>"",9,"") | G26: =IF(N(E26)=0,"",ROUND(IF(N(D26)>0,D26,1)*E26*(1-N(F26)),Decimales))
B27: =IF(C27<>"",10,"") | G27: =IF(N(E27)=0,"",ROUND(IF(N(D27)>0,D27,1)*E27*(1-N(F27)),Decimales))
B28: =IF(C28<>"",11,"") | G28: =IF(N(E28)=0,"",ROUND(IF(N(D28)>0,D28,1)*E28*(1-N(F28)),Decimales))
B29: =IF(C29<>"",12,"") | G29: =IF(N(E29)=0,"",ROUND(IF(N(D29)>0,D29,1)*E29*(1-N(F29)),Decimales))
B31: Condiciones y observaciones | E31: Subtotal (sin IVA) | G31: =IF(P10=1,P11-G32,P11)
B32: Forma de pago: a convenir. | E32: ="IVA "&IF(G14="Sin IVA","",G14) | G32: =IF(P9=0,0,IF(P10=1,ROUND(P11*P9/(1+P9),Decimales),ROUND(P11*P9,Decimales)))
E33: ="TOTAL "&Moneda | G33: =G31+G32
B37: Firma del emisor | E37: Conforme del cliente
B39: =IF(N(G33)=0,"Escribí los ítems y el IVA y el total se calculan solos.","✔ Presupuesto listo. Anotalo en HISTORIAL para llevar el seguimiento.")
B42: MIX SHOP DIGITAL · Herramientas inteligentes que simplifican tu vida.
B43: Versión gratuita · Para gestionar todo tu negocio en un solo lugar, conocé Mi Negocio PY → mixshopdigital.com.py

Sheet RECIBO
B1: MIX SHOP DIGITAL | D1: RECIBO
B2: Herramientas inteligentes que simplifican tu vida. | D2: Constancia de pago
C4: Completá lo que quieras: si dejás celdas vacías, se toman los datos del presupuesto.
B5: ← Presupuesto | D5: Historial | F5: Panel
B7: 1. COMPLETÁ (todo es opcional salvo el N°)
B8: Recibo N° | F8: Fecha | P8: =IF(N(D10)>0,D10,N(PRESUPUESTO!G33))
B9: Recibí de
B10: Monto recibido | F10: Pago | G10: Efectivo
B11: Concepto
B12: Vacío = se usan el cliente, el total y el N° del presupuesto.
B14: 2. RECIBO (lo que se imprime)
B15: =UPPER(NombreNegocio)&IF(RucNegocio="",""," · RUC "&RucNegocio)
B16: ="RECIBO N° "&IF(D8="","____",D8) | E16: =IF(N(G8)=0,"Fecha: ____","Fecha: "&RIGHT("0"&DAY(G8),2)&"/"&RIGHT("0"&MONTH(G8),2)&"/"&YEAR(G8))
B17: Recibí de | D17: =IF(D9<>"",D9,IF(PRESUPUESTO!D12<>"",PRESUPUESTO!D12,"____________________"))
B18: La suma de | D18: =FIXED(P8,Decimales)&" "&Moneda
B19: Por concepto de | D19: =IF(D11<>"",D11,IF(PRESUPUESTO!D11<>"","Pago del presupuesto N° "&PRESUPUESTO!D11,"Pago a cuenta"))
B20: Forma de pago | D20: =IF(G10="","Efectivo",G10)
B21: Total del presupuesto | D21: =IF(N(PRESUPUESTO!G33)=0,"-",FIXED(PRESUPUESTO!G33,Decimales)&" "&Moneda)
B22: Saldo pendiente | D22: =IF(N(PRESUPUESTO!G33)=0,"-",IF(PRESUPUESTO!G33-P8<=0,"Pago total — sin saldo",FIXED(PRESUPUESTO!G33-P8,Decimales)&" "&Moneda&" (pago parcial)"))
B24: Firma y aclaración | E24: Recibí conforme
B28: MIX SHOP DIGITAL · Herramientas inteligentes que simplifican tu vida.
B29: Versión gratuita · Para gestionar todo tu negocio en un solo lugar, conocé Mi Negocio PY → mixshopdigital.com.py

Sheet HISTORIAL
B1: MIX SHOP DIGITAL | E1: HISTORIAL
B2: Herramientas inteligentes que simplifican tu vida. | E2: Seguimiento de tus presupuestos
C4: Una fila por presupuesto enviado. Cambiá el Estado cuando se apruebe o se cobre. Podés filtrar con la fila de títulos.
B5: ← Presupuesto | D5: Ver panel →
B6: ="Registros: "&COUNT(F8:F107)&" de 100 · Por cobrar: "&FIXED(PANEL!E17,Decimales)&" "&Moneda
B7: N° | C7: Fecha | D7: Cliente | E7: Detalle (opcional) | F7: Monto total | G7: Estado
B110: MIX SHOP DIGITAL · Herramientas inteligentes que simplifican tu vida.
B111: Versión gratuita · Para gestionar todo tu negocio en un solo lugar, conocé Mi Negocio PY → mixshopdigital.com.py

Sheet PANEL
B1: MIX SHOP DIGITAL | F1: PANEL
B2: Herramientas inteligentes que simplifican tu vida. | F2: Tus presupuestos de un vistazo
B4: ← VOLVER | C4: El panel se arma solo con lo que anotás en HISTORIAL. No hace falta escribir nada acá.
B5: + Anotar presupuesto | E5: Presupuesto | G5: Ajustes | I5: Ayuda
B6: ="Año de control: "&AnioCtl&" · "&NombreNegocio
B8: PRESUPUESTADO | E8: POR COBRAR (aprobado) | H8: COBRADO | K8: TASA DE ÉXITO
B9: =E21 | E9: =E17 | H9: =E18 | K9: =IF((D17+D18+D19)=0,0,(D17+D18)/(D17+D18+D19))
B10: =Moneda | E10: =Moneda | H10: =Moneda | K10: aprobados ÷ respondidos
B12: =IF(E21=0,"Anotá tus presupuestos en la hoja HISTORIAL para ver tu panel.",IF(E17>0,"⚠ Tenés "&FIXED(E17,Decimales)&" "&Moneda&" aprobados esperando que los cobres.",IF(D16>0,"✔ Todo lo aprobado está cobrado. Te quedan "&D16&" presupuesto(s) esperando respuesta.","✔ Todo lo aprobado está cobrado.")))
B14: POR ESTADO (año elegido)
B15: Estado | D15: Cant. | E15: Monto | F15: %
B16: Enviado | D16: =COUNTIFS(HISTORIAL!$G$8:$G$107,B16,HISTORIAL!$C$8:$C$107,">="&DATE(AnioCtl,1,1),HISTORIAL!$C$8:$C$107,"<"&DATE(AnioCtl+1,1,1)) | E16: =SUMIFS(HISTORIAL!$F$8:$F$107,HISTORIAL!$G$8:$G$107,B16,HISTORIAL!$C$8:$C$107,">="&DATE(AnioCtl,1,1),HISTORIAL!$C$8:$C$107,"<"&DATE(AnioCtl+1,1,1)) | F16: =IF($E$21=0,0,E16/$E$21)
B17: Aprobado | D17: =COUNTIFS(HISTORIAL!$G$8:$G$107,B17,HISTORIAL!$C$8:$C$107,">="&DATE(AnioCtl,1,1),HISTORIAL!$C$8:$C$107,"<"&DATE(AnioCtl+1,1,1)) | E17: =SUMIFS(HISTORIAL!$F$8:$F$107,HISTORIAL!$G$8:$G$107,B17,HISTORIAL!$C$8:$C$107,">="&DATE(AnioCtl,1,1),HISTORIAL!$C$8:$C$107,"<"&DATE(AnioCtl+1,1,1)) | F17: =IF($E$21=0,0,E17/$E$21)
B18: Cobrado | D18: =COUNTIFS(HISTORIAL!$G$8:$G$107,B18,HISTORIAL!$C$8:$C$107,">="&DATE(AnioCtl,1,1),HISTORIAL!$C$8:$C$107,"<"&DATE(AnioCtl+1,1,1)) | E18: =SUMIFS(HISTORIAL!$F$8:$F$107,HISTORIAL!$G$8:$G$107,B18,HISTORIAL!$C$8:$C$107,">="&DATE(AnioCtl,1,1),HISTORIAL!$C$8:$C$107,"<"&DATE(AnioCtl+1,1,1)) | F18: =IF($E$21=0,0,E18/$E$21)
B19: Rechazado | D19: =COUNTIFS(HISTORIAL!$G$8:$G$107,B19,HISTORIAL!$C$8:$C$107,">="&DATE(AnioCtl,1,1),HISTORIAL!$C$8:$C$107,"<"&DATE(AnioCtl+1,1,1)) | E19: =SUMIFS(HISTORIAL!$F$8:$F$107,HISTORIAL!$G$8:$G$107,B19,HISTORIAL!$C$8:$C$107,">="&DATE(AnioCtl,1,1),HISTORIAL!$C$8:$C$107,"<"&DATE(AnioCtl+1,1,1)) | F19: =IF($E$21=0,0,E19/$E$21)
B21: TOTAL | D21: =SUM(D16:D19) | E21: =SUM(E16:E19) | F21: =SUM(F16:F19)
B23: MES A MES
B24: Mes | C24: Cant. | D24: Presup. | E24: Cobrado
B25: Enero | C25: =COUNTIFS(HISTORIAL!$C$8:$C$107,">="&DATE(AnioCtl,1,1),HISTORIAL!$C$8:$C$107,"<"&DATE(AnioCtl,2,1)) | D25: =SUMIFS(HISTORIAL!$F$8:$F$107,HISTORIAL!$C$8:$C$107,">="&DATE(AnioCtl,1,1),HISTORIAL!$C$8:$C$107,"<"&DATE(AnioCtl,2,1)) | E25: =SUMIFS(HISTORIAL!$F$8:$F$107,HISTORIAL!$G$8:$G$107,"Cobrado",HISTORIAL!$C$8:$C$107,">="&DATE(AnioCtl,1,1),HISTORIAL!$C$8:$C$107,"<"&DATE(AnioCtl,2,1))
B26: Febrero | C26: =COUNTIFS(HISTORIAL!$C$8:$C$107,">="&DATE(AnioCtl,2,1),HISTORIAL!$C$8:$C$107,"<"&DATE(AnioCtl,3,1)) | D26: =SUMIFS(HISTORIAL!$F$8:$F$107,HISTORIAL!$C$8:$C$107,">="&DATE(AnioCtl,2,1),HISTORIAL!$C$8:$C$107,"<"&DATE(AnioCtl,3,1)) | E26: =SUMIFS(HISTORIAL!$F$8:$F$107,HISTORIAL!$G$8:$G$107,"Cobrado",HISTORIAL!$C$8:$C$107,">="&DATE(AnioCtl,2,1),HISTORIAL!$C$8:$C$107,"<"&DATE(AnioCtl,3,1))
B27: Marzo | C27: =COUNTIFS(HISTORIAL!$C$8:$C$107,">="&DATE(AnioCtl,3,1),HISTORIAL!$C$8:$C$107,"<"&DATE(AnioCtl,4,1)) | D27: =SUMIFS(HISTORIAL!$F$8:$F$107,HISTORIAL!$C$8:$C$107,">="&DATE(AnioCtl,3,1),HISTORIAL!$C$8:$C$107,"<"&DATE(AnioCtl,4,1)) | E27: =SUMIFS(HISTORIAL!$F$8:$F$107,HISTORIAL!$G$8:$G$107,"Cobrado",HISTORIAL!$C$8:$C$107,">="&DATE(AnioCtl,3,1),HISTORIAL!$C$8:$C$107,"<"&DATE(AnioCtl,4,1))
B28: Abril | C28: =COUNTIFS(HISTORIAL!$C$8:$C$107,">="&DATE(AnioCtl,4,1),HISTORIAL!$C$8:$C$107,"<"&DATE(AnioCtl,5,1)) | D28: =SUMIFS(HISTORIAL!$F$8:$F$107,HISTORIAL!$C$8:$C$107,">="&DATE(AnioCtl,4,1),HISTORIAL!$C$8:$C$107,"<"&DATE(AnioCtl,5,1)) | E28: =SUMIFS(HISTORIAL!$F$8:$F$107,HISTORIAL!$G$8:$G$107,"Cobrado",HISTORIAL!$C$8:$C$107,">="&DATE(AnioCtl,4,1),HISTORIAL!$C$8:$C$107,"<"&DATE(AnioCtl,5,1))
B29: Mayo | C29: =COUNTIFS(HISTORIAL!$C$8:$C$107,">="&DATE(AnioCtl,5,1),HISTORIAL!$C$8:$C$107,"<"&DATE(AnioCtl,6,1)) | D29: =SUMIFS(HISTORIAL!$F$8:$F$107,HISTORIAL!$C$8:$C$107,">="&DATE(AnioCtl,5,1),HISTORIAL!$C$8:$C$107,"<"&DATE(AnioCtl,6,1)) | E29: =SUMIFS(HISTORIAL!$F$8:$F$107,HISTORIAL!$G$8:$G$107,"Cobrado",HISTORIAL!$C$8:$C$107,">="&DATE(AnioCtl,5,1),HISTORIAL!$C$8:$C$107,"<"&DATE(AnioCtl,6,1))
B30: Junio | C30: =COUNTIFS(HISTORIAL!$C$8:$C$107,">="&DATE(AnioCtl,6,1),HISTORIAL!$C$8:$C$107,"<"&DATE(AnioCtl,7,1)) | D30: =SUMIFS(HISTORIAL!$F$8:$F$107,HISTORIAL!$C$8:$C$107,">="&DATE(AnioCtl,6,1),HISTORIAL!$C$8:$C$107,"<"&DATE(AnioCtl,7,1)) | E30: =SUMIFS(HISTORIAL!$F$8:$F$107,HISTORIAL!$G$8:$G$107,"Cobrado",HISTORIAL!$C$8:$C$107,">="&DATE(AnioCtl,6,1),HISTORIAL!$C$8:$C$107,"<"&DATE(AnioCtl,7,1))
B31: Julio | C31: =COUNTIFS(HISTORIAL!$C$8:$C$107,">="&DATE(AnioCtl,7,1),HISTORIAL!$C$8:$C$107,"<"&DATE(AnioCtl,8,1)) | D31: =SUMIFS(HISTORIAL!$F$8:$F$107,HISTORIAL!$C$8:$C$107,">="&DATE(AnioCtl,7,1),HISTORIAL!$C$8:$C$107,"<"&DATE(AnioCtl,8,1)) | E31: =SUMIFS(HISTORIAL!$F$8:$F$107,HISTORIAL!$G$8:$G$107,"Cobrado",HISTORIAL!$C$8:$C$107,">="&DATE(AnioCtl,7,1),HISTORIAL!$C$8:$C$107,"<"&DATE(AnioCtl,8,1))
B32: Agosto | C32: =COUNTIFS(HISTORIAL!$C$8:$C$107,">="&DATE(AnioCtl,8,1),HISTORIAL!$C$8:$C$107,"<"&DATE(AnioCtl,9,1)) | D32: =SUMIFS(HISTORIAL!$F$8:$F$107,HISTORIAL!$C$8:$C$107,">="&DATE(AnioCtl,8,1),HISTORIAL!$C$8:$C$107,"<"&DATE(AnioCtl,9,1)) | E32: =SUMIFS(HISTORIAL!$F$8:$F$107,HISTORIAL!$G$8:$G$107,"Cobrado",HISTORIAL!$C$8:$C$107,">="&DATE(AnioCtl,8,1),HISTORIAL!$C$8:$C$107,"<"&DATE(AnioCtl,9,1))
B33: Septiembre | C33: =COUNTIFS(HISTORIAL!$C$8:$C$107,">="&DATE(AnioCtl,9,1),HISTORIAL!$C$8:$C$107,"<"&DATE(AnioCtl,10,1)) | D33: =SUMIFS(HISTORIAL!$F$8:$F$107,HISTORIAL!$C$8:$C$107,">="&DATE(AnioCtl,9,1),HISTORIAL!$C$8:$C$107,"<"&DATE(AnioCtl,10,1)) | E33: =SUMIFS(HISTORIAL!$F$8:$F$107,HISTORIAL!$G$8:$G$107,"Cobrado",HISTORIAL!$C$8:$C$107,">="&DATE(AnioCtl,9,1),HISTORIAL!$C$8:$C$107,"<"&DATE(AnioCtl,10,1))
B34: Octubre | C34: =COUNTIFS(HISTORIAL!$C$8:$C$107,">="&DATE(AnioCtl,10,1),HISTORIAL!$C$8:$C$107,"<"&DATE(AnioCtl,11,1)) | D34: =SUMIFS(HISTORIAL!$F$8:$F$107,HISTORIAL!$C$8:$C$107,">="&DATE(AnioCtl,10,1),HISTORIAL!$C$8:$C$107,"<"&DATE(AnioCtl,11,1)) | E34: =SUMIFS(HISTORIAL!$F$8:$F$107,HISTORIAL!$G$8:$G$107,"Cobrado",HISTORIAL!$C$8:$C$107,">="&DATE(AnioCtl,10,1),HISTORIAL!$C$8:$C$107,"<"&DATE(AnioCtl,11,1))
B35: Noviembre | C35: =COUNTIFS(HISTORIAL!$C$8:$C$107,">="&DATE(AnioCtl,11,1),HISTORIAL!$C$8:$C$107,"<"&DATE(AnioCtl,12,1)) | D35: =SUMIFS(HISTORIAL!$F$8:$F$107,HISTORIAL!$C$8:$C$107,">="&DATE(AnioCtl,11,1),HISTORIAL!$C$8:$C$107,"<"&DATE(AnioCtl,12,1)) | E35: =SUMIFS(HISTORIAL!$F$8:$F$107,HISTORIAL!$G$8:$G$107,"Cobrado",HISTORIAL!$C$8:$C$107,">="&DATE(AnioCtl,11,1),HISTORIAL!$C$8:$C$107,"<"&DATE(AnioCtl,12,1))
B36: Diciembre | C36: =COUNTIFS(HISTORIAL!$C$8:$C$107,">="&DATE(AnioCtl,12,1),HISTORIAL!$C$8:$C$107,"<"&DATE(AnioCtl,13,1)) | D36: =SUMIFS(HISTORIAL!$F$8:$F$107,HISTORIAL!$C$8:$C$107,">="&DATE(AnioCtl,12,1),HISTORIAL!$C$8:$C$107,"<"&DATE(AnioCtl,13,1)) | E36: =SUMIFS(HISTORIAL!$F$8:$F$107,HISTORIAL!$G$8:$G$107,"Cobrado",HISTORIAL!$C$8:$C$107,">="&DATE(AnioCtl,12,1),HISTORIAL!$C$8:$C$107,"<"&DATE(AnioCtl,13,1))
B37: TOTAL | C37: =SUM(C25:C36) | D37: =SUM(D25:D36) | E37: =SUM(E25:E36)
B48: MIX SHOP DIGITAL · Herramientas inteligentes que simplifican tu vida.
B49: Versión gratuita · Para gestionar todo tu negocio en un solo lugar, conocé Mi Negocio PY → mixshopdigital.com.py

Sheet AJUSTES
B1: MIX SHOP DIGITAL | C1: AJUSTES
B2: Herramientas inteligentes que simplifican tu vida. | C2: Cargalos una sola vez
B4: ← VOLVER | C4: Completá solamente las celdas amarillas. Estos datos aparecen en tus presupuestos y recibos.
B6: 1. TU NEGOCIO
B7: Nombre del negocio | C7: Mi negocio | D7: Aparece arriba en el presupuesto y el recibo.
B8: RUC o C.I. | D8: Opcional.
B9: Teléfono | D9: Opcional.
B10: Dirección o ciudad | D10: Opcional.
B11: Moneda | C11: Gs. | D11: Símbolo que se muestra en las hojas.
B12: Año a controlar | C12: 2026 | D12: El PANEL muestra los 12 meses de este año.
B13: Validez del presupuesto (días) | C13: 15 | D13: Se usa para calcular la fecha «Válido hasta».
B14: Decimales (automático) | C14: =IF(Moneda="Gs.",0,2) | D14: El guaraní no usa decimales; otras monedas usan 2.
B16: 2. TASAS DE IVA (fijadas por ley)
B17: Tasa general | C17: 0.1 | D17: 10 % — Ley 125/91, modificada por la Ley 6380/2019.
B18: Tasa reducida | C18: 0.05 | D18: 5 % — productos y servicios con tasa reducida.
B22: MIX SHOP DIGITAL · Herramientas inteligentes que simplifican tu vida.
B23: Versión gratuita · Para gestionar todo tu negocio en un solo lugar, conocé Mi Negocio PY → mixshopdigital.com.py

Sheet AYUDA
B1: MIX SHOP DIGITAL | D1: AYUDA
B2: Herramientas inteligentes que simplifican tu vida. | D2: Se aprende en 2 minutos
B4: ← VOLVER | C4: Leé esta hoja una vez. Después ya no la vas a necesitar.
B6: ¿PARA QUÉ SIRVE?
B7: Para armar un presupuesto prolijo, darle un recibo a tu cliente y saber cuánto tenés enviado, aprobado y cobrado. Sin fórmulas y sin Internet.
B9: EMPEZÁ EN 4 PASOS
B10: 1) En AJUSTES poné el nombre de tu negocio, tus datos y la validez de tus presupuestos.
B11: 2) En PRESUPUESTO completá los datos del cliente y los ítems. El IVA y el total se calculan solos. Después imprimilo o guardalo en PDF (Archivo > Imprimir).
B12: 3) Anotá el presupuesto en HISTORIAL y cambiá su estado cuando lo aprueben o lo cobren.
B13: 4) Cuando te paguen, completá el RECIBO. Si dejás celdas vacías, usa el cliente y el total del presupuesto.
B15: COLORES
B16: Rosado claro: celdas que completás vos. Gris o blanco: se calcula solo (bloqueado). Vino: títulos y totales. Verde: cobrado.
B18: PREGUNTAS FRECUENTES
B19: • Veo todo en cero: hacé clic en «Habilitar edición» en la barra amarilla de Excel.
B20: • ¿Cómo hago otro presupuesto? Guardá una copia del archivo y borrá los ítems y datos del cliente (celdas rosadas), o escribí encima.
... B35: Versión gratuita · Para gestionar todo tu negocio en un solo lugar, conocé Mi Negocio PY → mixshopdigital.com.py
