Workbook
Name NombreHogar: 'AJUSTES'!$C$7
Name AnioCtl: 'AJUSTES'!$C$8
Name Moneda: 'AJUSTES'!$C$9
Name PresMes: 'AJUSTES'!$C$10
Name ListaCat: 'AJUSTES'!$B$14:$B$21
Name MesN: 'PANEL'!$P$6

Sheet PANEL
F1: SERVICIOS Y GASTOS DEL HOGAR
B2: Herramientas inteligentes que simplifican tu vida. | F2: Tu hogar, de un vistazo
C4: El panel se arma solo con lo que anotás en SERVICIOS. No hace falta escribir nada acá, salvo elegir el período.
B5: + Anotar pagos | E5: Vencimientos | G5: Ajustes | I5: Ayuda
B6: Período a mirar: | C6: Todo el año | E6: ="Año de control: "&AnioCtl&" · "&NombreHogar | P6: =IFERROR(MATCH(C6,{"Todo el año","Enero","Febrero","Marzo","Abril","Mayo","Junio","Julio","Agosto","Septiembre","Octubre","Noviembre","Diciembre"},0)-1,0)
B8: GASTO DEL PERÍODO | E8: PROMEDIO POR MES | H8: VS. TU PRESUPUESTO | K8: GASTO MÁS GRANDE
B9: =IF(MesN=0,C29,INDEX(C17:C28,MesN)) | E9: =IFERROR(C29/COUNTIF(C17:C28,">0"),0) | H9: =IF(PresMes=0,"-",IF(MesN=0,E29,INDEX(E17:E28,MesN))) | K9: =IF(MAX(P17:P36)<=0,"-",INDEX(SERVICIOS!B8:B27,MATCH(MAX(P17:P36),P17:P36,0)))
B10: =Moneda | E10: meses con gastos cargados | H10: positivo: te sobró · negativo: te pasaste | K10: en el período
B12: =IF(C29=0,"Cargá tus pagos en la hoja SERVICIOS para ver tu panel.",IF(AND(ISNUMBER(H9),H9<0),"⚠ Te pasaste del presupuesto por "&FIXED(-H9,0)&" "&Moneda&" en este período.",IF(ISNUMBER(H9),"✔ Estás dentro de tu presupuesto.","✔ Tus gastos están cargados. Poné un presupuesto en AJUSTES para compararlo.")))
B13: ="Este mes: "&VENCIMIENTOS!B8&" pagado(s) · "&VENCIMIENTOS!D8&" pendiente(s) · a pagar aprox. "&FIXED(VENCIMIENTOS!F8,0)&" "&Moneda&" (detalle en VENCIMIENTOS)"
B15: MES A MES
B16: Mes | C16: Gasto | D16: Presupuesto | E16: Diferencia
B17: Enero | C17: =SERVICIOS!E28 | D17: =PresMes | E17: =IF(OR(PresMes=0,C17=0),0,D17-C17) | P17: =IF(SERVICIOS!B8="",0,IF(MesN=0,N(SERVICIOS!Q8),N(INDEX(SERVICIOS!E8:P8,MesN))))
B18: Febrero | C18: =SERVICIOS!F28 | D18: =PresMes | E18: =IF(OR(PresMes=0,C18=0),0,D18-C18) | P18: =IF(SERVICIOS!B9="",0,IF(MesN=0,N(SERVICIOS!Q9),N(INDEX(SERVICIOS!E9:P9,MesN))))
B19: Marzo | C19: =SERVICIOS!G28 | D19: =PresMes | E19: =IF(OR(PresMes=0,C19=0),0,D19-C19) | P19: =IF(SERVICIOS!B10="",0,IF(MesN=0,N(SERVICIOS!Q10),N(INDEX(SERVICIOS!E10:P10,MesN))))
B20: Abril | C20: =SERVICIOS!H28 | D20: =PresMes | E20: =IF(OR(PresMes=0,C20=0),0,D20-C20) | P20: =IF(SERVICIOS!B11="",0,IF(MesN=0,N(SERVICIOS!Q11),N(INDEX(SERVICIOS!E11:P11,MesN))))
B21: Mayo | C21: =SERVICIOS!I28 | D21: =PresMes | E21: =IF(OR(PresMes=0,C21=0),0,D21-C21) | P21: =IF(SERVICIOS!B12="",0,IF(MesN=0,N(SERVICIOS!Q12),N(INDEX(SERVICIOS!E12:P12,MesN))))
B22: Junio | C22: =SERVICIOS!J28 | D22: =PresMes | E22: =IF(OR(PresMes=0,C22=0),0,D22-C22) | P22: =IF(SERVICIOS!B13="",0,IF(MesN=0,N(SERVICIOS!Q13),N(INDEX(SERVICIOS!E13:P13,MesN))))
B23: Julio | C23: =SERVICIOS!K28 | D23: =PresMes | E23: =IF(OR(PresMes=0,C23=0),0,D23-C23) | P23: =IF(SERVICIOS!B14="",0,IF(MesN=0,N(SERVICIOS!Q14),N(INDEX(SERVICIOS!E14:P14,MesN))))
B24: Agosto | C24: =SERVICIOS!L28 | D24: =PresMes | E24: =IF(OR(PresMes=0,C24=0),0,D24-C24) | P24: =IF(SERVICIOS!B15="",0,IF(MesN=0,N(SERVICIOS!Q15),N(INDEX(SERVICIOS!E15:P15,MesN))))
B25: Septiembre | C25: =SERVICIOS!M28 | D25: =PresMes | E25: =IF(OR(PresMes=0,C25=0),0,D25-C25) | P25: =IF(SERVICIOS!B16="",0,IF(MesN=0,N(SERVICIOS!Q16),N(INDEX(SERVICIOS!E16:P16,MesN))))
B26: Octubre | C26: =SERVICIOS!N28 | D26: =PresMes | E26: =IF(OR(PresMes=0,C26=0),0,D26-C26) | P26: =IF(SERVICIOS!B17="",0,IF(MesN=0,N(SERVICIOS!Q17),N(INDEX(SERVICIOS!E17:P17,MesN))))
B27: Noviembre | C27: =SERVICIOS!O28 | D27: =PresMes | E27: =IF(OR(PresMes=0,C27=0),0,D27-C27) | P27: =IF(SERVICIOS!B18="",0,IF(MesN=0,N(SERVICIOS!Q18),N(INDEX(SERVICIOS!E18:P18,MesN))))
B28: Diciembre | C28: =SERVICIOS!P28 | D28: =PresMes | E28: =IF(OR(PresMes=0,C28=0),0,D28-C28) | P28: =IF(SERVICIOS!B19="",0,IF(MesN=0,N(SERVICIOS!Q19),N(INDEX(SERVICIOS!E19:P19,MesN))))
B29: TOTAL | C29: =SUM(C17:C28) | D29: =SUM(D17:D28) | E29: =SUM(E17:E28) | P29: =IF(SERVICIOS!B20="",0,IF(MesN=0,N(SERVICIOS!Q20),N(INDEX(SERVICIOS!E20:P20,MesN))))
P30: =IF(SERVICIOS!B21="",0,IF(MesN=0,N(SERVICIOS!Q21),N(INDEX(SERVICIOS!E21:P21,MesN))))
B31: POR CATEGORÍA (período elegido) | P31: =IF(SERVICIOS!B22="",0,IF(MesN=0,N(SERVICIOS!Q22),N(INDEX(SERVICIOS!E22:P22,MesN))))
B32: Categoría | D32: Monto | E32: % | P32: =IF(SERVICIOS!B23="",0,IF(MesN=0,N(SERVICIOS!Q23),N(INDEX(SERVICIOS!E23:P23,MesN))))
B33: =IF('AJUSTES'!$B$14="","",'AJUSTES'!$B$14) | D33: =IF(B33="",0,IF(MesN=0,SUMIF(SERVICIOS!$C$8:$C$27,B33,SERVICIOS!$Q$8:$Q$27),SUMIF(SERVICIOS!$C$8:$C$27,B33,INDEX(SERVICIOS!$E$8:$P$27,0,MesN)))) | E33: =IF($D$41=0,0,D33/$D$41) | P33: =IF(SERVICIOS!B24="",0,IF(MesN=0,N(SERVICIOS!Q24),N(INDEX(SERVICIOS!E24:P24,MesN))))
B34: =IF('AJUSTES'!$B$15="","",'AJUSTES'!$B$15) | D34: =IF(B34="",0,IF(MesN=0,SUMIF(SERVICIOS!$C$8:$C$27,B34,SERVICIOS!$Q$8:$Q$27),SUMIF(SERVICIOS!$C$8:$C$27,B34,INDEX(SERVICIOS!$E$8:$P$27,0,MesN)))) | E34: =IF($D$41=0,0,D34/$D$41) | P34: =IF(SERVICIOS!B25="",0,IF(MesN=0,N(SERVICIOS!Q25),N(INDEX(SERVICIOS!E25:P25,MesN))))
B35: =IF('AJUSTES'!$B$16="","",'AJUSTES'!$B$16) | D35: =IF(B35="",0,IF(MesN=0,SUMIF(SERVICIOS!$C$8:$C$27,B35,SERVICIOS!$Q$8:$Q$27),SUMIF(SERVICIOS!$C$8:$C$27,B35,INDEX(SERVICIOS!$E$8:$P$27,0,MesN)))) | E35: =IF($D$41=0,0,D35/$D$41) | P35: =IF(SERVICIOS!B26="",0,IF(MesN=0,N(SERVICIOS!Q26),N(INDEX(SERVICIOS!E26:P26,MesN))))
B36: =IF('AJUSTES'!$B$17="","",'AJUSTES'!$B$17) | D36: =IF(B36="",0,IF(MesN=0,SUMIF(SERVICIOS!$C$8:$C$27,B36,SERVICIOS!$Q$8:$Q$27),SUMIF(SERVICIOS!$C$8:$C$27,B36,INDEX(SERVICIOS!$E$8:$P$27,0,MesN)))) | E36: =IF($D$41=0,0,D36/$D$41) | P36: =IF(SERVICIOS!B27="",0,IF(MesN=0,N(SERVICIOS!Q27),N(INDEX(SERVICIOS!E27:P27,MesN))))
B37: =IF('AJUSTES'!$B$18="","",'AJUSTES'!$B$18) | D37: =IF(B37="",0,IF(MesN=0,SUMIF(SERVICIOS!$C$8:$C$27,B37,SERVICIOS!$Q$8:$Q$27),SUMIF(SERVICIOS!$C$8:$C$27,B37,INDEX(SERVICIOS!$E$8:$P$27,0,MesN)))) | E37: =IF($D$41=0,0,D37/$D$41)
B38: =IF('AJUSTES'!$B$19="","",'AJUSTES'!$B$19) | D38: =IF(B38="",0,IF(MesN=0,SUMIF(SERVICIOS!$C$8:$C$27,B38,SERVICIOS!$Q$8:$Q$27),SUMIF(SERVICIOS!$C$8:$C$27,B38,INDEX(SERVICIOS!$E$8:$P$27,0,MesN)))) | E38: =IF($D$41=0,0,D38/$D$41)
B39: =IF('AJUSTES'!$B$20="","",'AJUSTES'!$B$20) | D39: =IF(B39="",0,IF(MesN=0,SUMIF(SERVICIOS!$C$8:$C$27,B39,SERVICIOS!$Q$8:$Q$27),SUMIF(SERVICIOS!$C$8:$C$27,B39,INDEX(SERVICIOS!$E$8:$P$27,0,MesN)))) | E39: =IF($D$41=0,0,D39/$D$41)
B40: =IF('AJUSTES'!$B$21="","",'AJUSTES'!$B$21) | D40: =IF(B40="",0,IF(MesN=0,SUMIF(SERVICIOS!$C$8:$C$27,B40,SERVICIOS!$Q$8:$Q$27),SUMIF(SERVICIOS!$C$8:$C$27,B40,INDEX(SERVICIOS!$E$8:$P$27,0,MesN)))) | E40: =IF($D$41=0,0,D40/$D$41)
B41: TOTAL | D41: =SUM(D33:D40) | E41: =SUM(E33:E40)
B48: MIX SHOP DIGITAL · Herramientas inteligentes que simplifican tu vida.
B49: Versión gratuita · Más herramientas gratuitas para tu vida diaria → mixshopdigital.com.py

Sheet SERVICIOS
F1: SERVICIOS
B2: Herramientas inteligentes que simplifican tu vida. | F2: Anotá lo que pagás cada mes
C4: Una fila por servicio o gasto fijo. Escribí cuánto pagaste en cada mes. Se pinta de naranja si sube más de 20 % respecto del mes anterior.
B5: ← Volver al PANEL | D5: Vencimientos
B7: Servicio o gasto | C7: Categoría | D7: Vence el día | E7: Ene | F7: Feb | G7: Mar | H7: Abr | I7: May | J7: Jun | K7: Jul | L7: Ago | M7: Sep | N7: Oct | O7: Nov | P7: Dic | Q7: Total del año | R7: Promedio por mes
B8: Agua | C8: Servicios básicos | D8: 10 | E8: 62000 | F8: 71000 | G8: 72000 | H8: 56000 | I8: 60000 | J8: 50000 | K8: 53000 | L8: 56000 | M8: 63000 | N8: 80000 | Q8: =IF($B8="","",SUM(E8:P8)) | R8: =IF($B8="","",IFERROR(Q8/COUNTIF(E8:P8,">0"),0))
B9: Luz | C9: Servicios básicos | D9: 15 | E9: 201000 | F9: 227000 | G9: 255000 | H9: 175000 | I9: 159000 | J9: 150000 | K9: 139000 | L9: 132000 | M9: 170000 | N9: 233000 | Q9: =IF($B9="","",SUM(E9:P9)) | R9: =IF($B9="","",IFERROR(Q9/COUNTIF(E9:P9,">0"),0))
B10: Gas | C10: Servicios básicos | D10: 20 | F10: 75000 | H10: 75000 | J10: 75000 | L10: 75000 | N10: 75000 | Q10: =IF($B10="","",SUM(E10:P10)) | R10: =IF($B10="","",IFERROR(Q10/COUNTIF(E10:P10,">0"),0))
B11: Internet | C11: Comunicaciones | D11: 31 | E11: 189000 | F11: 189000 | G11: 189000 | H11: 189000 | I11: 189000 | J11: 189000 | K11: 189000 | L11: 189000 | M11: 189000 | N11: 189000 | Q11: =IF($B11="","",SUM(E11:P11)) | R11: =IF($B11="","",IFERROR(Q11/COUNTIF(E11:P11,">0"),0))
B12: Cable / TV | C12: Comunicaciones | D12: 5 | E12: 125000 | F12: 125000 | G12: 125000 | H12: 125000 | I12: 125000 | J12: 125000 | K12: 125000 | L12: 125000 | M12: 125000 | Q12: =IF($B12="","",SUM(E12:P12)) | R12: =IF($B12="","",IFERROR(Q12/COUNTIF(E12:P12,">0"),0))
B13: Teléfono celular | C13: Comunicaciones | D13: 12 | E13: 80000 | F13: 80000 | G13: 80000 | H13: 80000 | I13: 80000 | J13: 80000 | K13: 80000 | L13: 80000 | M13: 80000 | N13: 80000 | Q13: =IF($B13="","",SUM(E13:P13)) | R13: =IF($B13="","",IFERROR(Q13/COUNTIF(E13:P13,">0"),0))
B14: Alquiler o cuota de la casa | C14: Vivienda | D14: 1 | E14: 2200000 | F14: 2200000 | G14: 2200000 | H14: 2200000 | I14: 2200000 | J14: 2200000 | K14: 2400000 | L14: 2400000 | M14: 2400000 | N14: 2400000 | Q14: =IF($B14="","",SUM(E14:P14)) | R14: =IF($B14="","",IFERROR(Q14/COUNTIF(E14:P14,">0"),0))
B15: Cuotas del colegio | C15: Educación | D15: 5 | G15: 650000 | H15: 650000 | I15: 650000 | J15: 650000 | K15: 650000 | L15: 650000 | M15: 650000 | N15: 650000 | Q15: =IF($B15="","",SUM(E15:P15)) | R15: =IF($B15="","",IFERROR(Q15/COUNTIF(E15:P15,">0"),0))
B16: Seguro médico | C16: Salud | D16: 8 | E16: 395000 | F16: 395000 | G16: 395000 | H16: 395000 | I16: 395000 | J16: 395000 | K16: 395000 | L16: 395000 | M16: 395000 | Q16: =IF($B16="","",SUM(E16:P16)) | R16: =IF($B16="","",IFERROR(Q16/COUNTIF(E16:P16,">0"),0))
B17: Otros gastos fijos | C17: Otros | D17: 25 | E17: 250000 | F17: 400000 | G17: 150000 | H17: 450000 | I17: 250000 | J17: 100000 | K17: 300000 | L17: 400000 | M17: 450000 | N17: 400000 | Q17: =IF($B17="","",SUM(E17:P17)) | R17: =IF($B17="","",IFERROR(Q17/COUNTIF(E17:P17,">0"),0))
Q18: =IF($B18="","",SUM(E18:P18)) | R18: =IF($B18="","",IFERROR(Q18/COUNTIF(E18:P18,">0"),0))
Q19: =IF($B19="","",SUM(E19:P19)) | R19: =IF($B19="","",IFERROR(Q19/COUNTIF(E19:P19,">0"),0))
Q20: =IF($B20="","",SUM(E20:P20)) | R20: =IF($B20="","",IFERROR(Q20/COUNTIF(E20:P20,">0"),0))
Q21: =IF($B21="","",SUM(E21:P21)) | R21: =IF($B21="","",IFERROR(Q21/COUNTIF(E21:P21,">0"),0))
Q22: =IF($B22="","",SUM(E22:P22)) | R22: =IF($B22="","",IFERROR(Q22/COUNTIF(E22:P22,">0"),0))
Q23: =IF($B23="","",SUM(E23:P23)) | R23: =IF($B23="","",IFERROR(Q23/COUNTIF(E23:P23,">0"),0))
Q24: =IF($B24="","",SUM(E24:P24)) | R24: =IF($B24="","",IFERROR(Q24/COUNTIF(E24:P24,">0"),0))
Q25: =IF($B25="","",SUM(E25:P25)) | R25: =IF($B25="","",IFERROR(Q25/COUNTIF(E25:P25,">0"),0))
Q26: =IF($B26="","",SUM(E26:P26)) | R26: =IF($B26="","",IFERROR(Q26/COUNTIF(E26:P26,">0"),0))
Q27: =IF($B27="","",SUM(E27:P27)) | R27: =IF($B27="","",IFERROR(Q27/COUNTIF(E27:P27,">0"),0))
B28: TOTAL DEL MES | E28: =SUM(E8:E27) | F28: =SUM(F8:F27) | G28: =SUM(G8:G27) | H28: =SUM(H8:H27) | I28: =SUM(I8:I27) | J28: =SUM(J8:J27) | K28: =SUM(K8:K27) | L28: =SUM(L8:L27) | ... Q28: =SUM(Q8:Q27) | R28: =IFERROR(Q28/COUNTIF(E28:P28,">0"),0)
B31: MIX SHOP DIGITAL · Herramientas inteligentes que simplifican tu vida.
B32: Versión gratuita · Más herramientas gratuitas para tu vida diaria → mixshopdigital.com.py

Sheet VENCIMIENTOS
D1: VENCIMIENTOS
B2: Herramientas inteligentes que simplifican tu vida. | D2: ¿Qué tenés que pagar este mes?
C4: Se arma solo con SERVICIOS: si ya cargaste el monto del mes figura como pagado; si no, te avisa cuándo vence.
B5: ← Volver al PANEL | D5: Anotar pagos
B7: PAGADOS ESTE MES | D7: PENDIENTES | F7: A PAGAR (APROX.)
B8: =COUNTIF(F11:F30,"✔*") | D8: =COUNTIF(B11:B30,"?*")-B8 | F8: =SUMIF(F11:F30,"<>✔ Pagado",G11:G30)
B9: ="de "&COUNTIF(B11:B30,"?*")&" servicios" | D9: todavía sin pagar | F9: según tu promedio
B10: Servicio | C10: Categoría | D10: Vence | E10: Pagaste este mes | F10: Estado | G10: Tu promedio
B11: =IF(SERVICIOS!B8="","",SERVICIOS!B8) | C11: =IF(B11="","",SERVICIOS!C8&"") | D11: =IF(OR(B11="",N(SERVICIOS!D8)=0),"",DATE(YEAR(TODAY()),MONTH(TODAY()),MIN(SERVICIOS!D8,DAY(DATE(YEAR(TODAY()),MONTH(TODAY())+1,0))))) | E11: =IF(B11="","",IF(YEAR(TODAY())<>AnioCtl,"",INDEX(SERVICIOS!E8:P8,MONTH(TODAY())))) | F11: =IF(B11="","",IF(YEAR(TODAY())<>AnioCtl,"Cambiá el año en AJUSTES",IF(N(E11)>0,"✔ Pagado",IF(D11="","Sin día de vencimiento",IF(D11<TODAY(),"✖ Vencido",IF(D11=TODAY(),"⚠ Vence hoy",IF(D11-TODAY()<=5,"⚠ Vence en "&(D11-TODAY())&" día(s)","Pendiente"))))))) | G11: =IF(B11="","",SERVICIOS!R8)
B12: =IF(SERVICIOS!B9="","",SERVICIOS!B9) | C12: =IF(B12="","",SERVICIOS!C9&"") | D12: =IF(OR(B12="",N(SERVICIOS!D9)=0),"",DATE(YEAR(TODAY()),MONTH(TODAY()),MIN(SERVICIOS!D9,DAY(DATE(YEAR(TODAY()),MONTH(TODAY())+1,0))))) | E12: =IF(B12="","",IF(YEAR(TODAY())<>AnioCtl,"",INDEX(SERVICIOS!E9:P9,MONTH(TODAY())))) | F12: =IF(B12="","",IF(YEAR(TODAY())<>AnioCtl,"Cambiá el año en AJUSTES",IF(N(E12)>0,"✔ Pagado",IF(D12="","Sin día de vencimiento",IF(D12<TODAY(),"✖ Vencido",IF(D12=TODAY(),"⚠ Vence hoy",IF(D12-TODAY()<=5,"⚠ Vence en "&(D12-TODAY())&" día(s)","Pendiente"))))))) | G12: =IF(B12="","",SERVICIOS!R9)
B13: =IF(SERVICIOS!B10="","",SERVICIOS!B10) | C13: =IF(B13="","",SERVICIOS!C10&"") | D13: =IF(OR(B13="",N(SERVICIOS!D10)=0),"",DATE(YEAR(TODAY()),MONTH(TODAY()),MIN(SERVICIOS!D10,DAY(DATE(YEAR(TODAY()),MONTH(TODAY())+1,0))))) | E13: =IF(B13="","",IF(YEAR(TODAY())<>AnioCtl,"",INDEX(SERVICIOS!E10:P10,MONTH(TODAY())))) | F13: =IF(B13="","",IF(YEAR(TODAY())<>AnioCtl,"Cambiá el año en AJUSTES",IF(N(E13)>0,"✔ Pagado",IF(D13="","Sin día de vencimiento",IF(D13<TODAY(),"✖ Vencido",IF(D13=TODAY(),"⚠ Vence hoy",IF(D13-TODAY()<=5,"⚠ Vence en "&(D13-TODAY())&" día(s)","Pendiente"))))))) | G13: =IF(B13="","",SERVICIOS!R10)
B14: =IF(SERVICIOS!B11="","",SERVICIOS!B11) | C14: =IF(B14="","",SERVICIOS!C11&"") | D14: =IF(OR(B14="",N(SERVICIOS!D11)=0),"",DATE(YEAR(TODAY()),MONTH(TODAY()),MIN(SERVICIOS!D11,DAY(DATE(YEAR(TODAY()),MONTH(TODAY())+1,0))))) | E14: =IF(B14="","",IF(YEAR(TODAY())<>AnioCtl,"",INDEX(SERVICIOS!E11:P11,MONTH(TODAY())))) | F14: =IF(B14="","",IF(YEAR(TODAY())<>AnioCtl,"Cambiá el año en AJUSTES",IF(N(E14)>0,"✔ Pagado",IF(D14="","Sin día de vencimiento",IF(D14<TODAY(),"✖ Vencido",IF(D14=TODAY(),"⚠ Vence hoy",IF(D14-TODAY()<=5,"⚠ Vence en "&(D14-TODAY())&" día(s)","Pendiente"))))))) | G14: =IF(B14="","",SERVICIOS!R11)
B15: =IF(SERVICIOS!B12="","",SERVICIOS!B12) | C15: =IF(B15="","",SERVICIOS!C12&"") | D15: =IF(OR(B15="",N(SERVICIOS!D12)=0),"",DATE(YEAR(TODAY()),MONTH(TODAY()),MIN(SERVICIOS!D12,DAY(DATE(YEAR(TODAY()),MONTH(TODAY())+1,0))))) | E15: =IF(B15="","",IF(YEAR(TODAY())<>AnioCtl,"",INDEX(SERVICIOS!E12:P12,MONTH(TODAY())))) | F15: =IF(B15="","",IF(YEAR(TODAY())<>AnioCtl,"Cambiá el año en AJUSTES",IF(N(E15)>0,"✔ Pagado",IF(D15="","Sin día de vencimiento",IF(D15<TODAY(),"✖ Vencido",IF(D15=TODAY(),"⚠ Vence hoy",IF(D15-TODAY()<=5,"⚠ Vence en "&(D15-TODAY())&" día(s)","Pendiente"))))))) | G15: =IF(B15="","",SERVICIOS!R12)
B16: =IF(SERVICIOS!B13="","",SERVICIOS!B13) | C16: =IF(B16="","",SERVICIOS!C13&"") | D16: =IF(OR(B16="",N(SERVICIOS!D13)=0),"",DATE(YEAR(TODAY()),MONTH(TODAY()),MIN(SERVICIOS!D13,DAY(DATE(YEAR(TODAY()),MONTH(TODAY())+1,0))))) | E16: =IF(B16="","",IF(YEAR(TODAY())<>AnioCtl,"",INDEX(SERVICIOS!E13:P13,MONTH(TODAY())))) | F16: =IF(B16="","",IF(YEAR(TODAY())<>AnioCtl,"Cambiá el año en AJUSTES",IF(N(E16)>0,"✔ Pagado",IF(D16="","Sin día de vencimiento",IF(D16<TODAY(),"✖ Vencido",IF(D16=TODAY(),"⚠ Vence hoy",IF(D16-TODAY()<=5,"⚠ Vence en "&(D16-TODAY())&" día(s)","Pendiente"))))))) | G16: =IF(B16="","",SERVICIOS!R13)
B17: =IF(SERVICIOS!B14="","",SERVICIOS!B14) | C17: =IF(B17="","",SERVICIOS!C14&"") | D17: =IF(OR(B17="",N(SERVICIOS!D14)=0),"",DATE(YEAR(TODAY()),MONTH(TODAY()),MIN(SERVICIOS!D14,DAY(DATE(YEAR(TODAY()),MONTH(TODAY())+1,0))))) | E17: =IF(B17="","",IF(YEAR(TODAY())<>AnioCtl,"",INDEX(SERVICIOS!E14:P14,MONTH(TODAY())))) | F17: =IF(B17="","",IF(YEAR(TODAY())<>AnioCtl,"Cambiá el año en AJUSTES",IF(N(E17)>0,"✔ Pagado",IF(D17="","Sin día de vencimiento",IF(D17<TODAY(),"✖ Vencido",IF(D17=TODAY(),"⚠ Vence hoy",IF(D17-TODAY()<=5,"⚠ Vence en "&(D17-TODAY())&" día(s)","Pendiente"))))))) | G17: =IF(B17="","",SERVICIOS!R14)
B18: =IF(SERVICIOS!B15="","",SERVICIOS!B15) | C18: =IF(B18="","",SERVICIOS!C15&"") | D18: =IF(OR(B18="",N(SERVICIOS!D15)=0),"",DATE(YEAR(TODAY()),MONTH(TODAY()),MIN(SERVICIOS!D15,DAY(DATE(YEAR(TODAY()),MONTH(TODAY())+1,0))))) | E18: =IF(B18="","",IF(YEAR(TODAY())<>AnioCtl,"",INDEX(SERVICIOS!E15:P15,MONTH(TODAY())))) | F18: =IF(B18="","",IF(YEAR(TODAY())<>AnioCtl,"Cambiá el año en AJUSTES",IF(N(E18)>0,"✔ Pagado",IF(D18="","Sin día de vencimiento",IF(D18<TODAY(),"✖ Vencido",IF(D18=TODAY(),"⚠ Vence hoy",IF(D18-TODAY()<=5,"⚠ Vence en "&(D18-TODAY())&" día(s)","Pendiente"))))))) | G18: =IF(B18="","",SERVICIOS!R15)
B19: =IF(SERVICIOS!B16="","",SERVICIOS!B16) | C19: =IF(B19="","",SERVICIOS!C16&"") | D19: =IF(OR(B19="",N(SERVICIOS!D16)=0),"",DATE(YEAR(TODAY()),MONTH(TODAY()),MIN(SERVICIOS!D16,DAY(DATE(YEAR(TODAY()),MONTH(TODAY())+1,0))))) | E19: =IF(B19="","",IF(YEAR(TODAY())<>AnioCtl,"",INDEX(SERVICIOS!E16:P16,MONTH(TODAY())))) | F19: =IF(B19="","",IF(YEAR(TODAY())<>AnioCtl,"Cambiá el año en AJUSTES",IF(N(E19)>0,"✔ Pagado",IF(D19="","Sin día de vencimiento",IF(D19<TODAY(),"✖ Vencido",IF(D19=TODAY(),"⚠ Vence hoy",IF(D19-TODAY()<=5,"⚠ Vence en "&(D19-TODAY())&" día(s)","Pendiente"))))))) | G19: =IF(B19="","",SERVICIOS!R16)
B20: =IF(SERVICIOS!B17="","",SERVICIOS!B17) | C20: =IF(B20="","",SERVICIOS!C17&"") | D20: =IF(OR(B20="",N(SERVICIOS!D17)=0),"",DATE(YEAR(TODAY()),MONTH(TODAY()),MIN(SERVICIOS!D17,DAY(DATE(YEAR(TODAY()),MONTH(TODAY())+1,0))))) | E20: =IF(B20="","",IF(YEAR(TODAY())<>AnioCtl,"",INDEX(SERVICIOS!E17:P17,MONTH(TODAY())))) | F20: =IF(B20="","",IF(YEAR(TODAY())<>AnioCtl,"Cambiá el año en AJUSTES",IF(N(E20)>0,"✔ Pagado",IF(D20="","Sin día de vencimiento",IF(D20<TODAY(),"✖ Vencido",IF(D20=TODAY(),"⚠ Vence hoy",IF(D20-TODAY()<=5,"⚠ Vence en "&(D20-TODAY())&" día(s)","Pendiente"))))))) | G20: =IF(B20="","",SERVICIOS!R17)
B21: =IF(SERVICIOS!B18="","",SERVICIOS!B18) | C21: =IF(B21="","",SERVICIOS!C18&"") | D21: =IF(OR(B21="",N(SERVICIOS!D18)=0),"",DATE(YEAR(TODAY()),MONTH(TODAY()),MIN(SERVICIOS!D18,DAY(DATE(YEAR(TODAY()),MONTH(TODAY())+1,0))))) | E21: =IF(B21="","",IF(YEAR(TODAY())<>AnioCtl,"",INDEX(SERVICIOS!E18:P18,MONTH(TODAY())))) | F21: =IF(B21="","",IF(YEAR(TODAY())<>AnioCtl,"Cambiá el año en AJUSTES",IF(N(E21)>0,"✔ Pagado",IF(D21="","Sin día de vencimiento",IF(D21<TODAY(),"✖ Vencido",IF(D21=TODAY(),"⚠ Vence hoy",IF(D21-TODAY()<=5,"⚠ Vence en "&(D21-TODAY())&" día(s)","Pendiente"))))))) | G21: =IF(B21="","",SERVICIOS!R18)
B22: =IF(SERVICIOS!B19="","",SERVICIOS!B19) | C22: =IF(B22="","",SERVICIOS!C19&"") | D22: =IF(OR(B22="",N(SERVICIOS!D19)=0),"",DATE(YEAR(TODAY()),MONTH(TODAY()),MIN(SERVICIOS!D19,DAY(DATE(YEAR(TODAY()),MONTH(TODAY())+1,0))))) | E22: =IF(B22="","",IF(YEAR(TODAY())<>AnioCtl,"",INDEX(SERVICIOS!E19:P19,MONTH(TODAY())))) | F22: =IF(B22="","",IF(YEAR(TODAY())<>AnioCtl,"Cambiá el año en AJUSTES",IF(N(E22)>0,"✔ Pagado",IF(D22="","Sin día de vencimiento",IF(D22<TODAY(),"✖ Vencido",IF(D22=TODAY(),"⚠ Vence hoy",IF(D22-TODAY()<=5,"⚠ Vence en "&(D22-TODAY())&" día(s)","Pendiente"))))))) | G22: =IF(B22="","",SERVICIOS!R19)
... B30: =IF(SERVICIOS!B27="","",SERVICIOS!B27) | C30: =IF(B30="","",SERVICIOS!C27&"") | D30: =IF(OR(B30="",N(SERVICIOS!D27)=0),"",DATE(YEAR(TODAY()),MONTH(TODAY()),MIN(SERVICIOS!D27,DAY(DATE(YEAR(TODAY()),MONTH(TODAY())+1,0))))) | E30: =IF(B30="","",IF(YEAR(TODAY())<>AnioCtl,"",INDEX(SERVICIOS!E27:P27,MONTH(TODAY())))) | F30: =IF(B30="","",IF(YEAR(TODAY())<>AnioCtl,"Cambiá el año en AJUSTES",IF(N(E30)>0,"✔ Pagado",IF(D30="","Sin día de vencimiento",IF(D30<TODAY(),"✖ Vencido",IF(D30=TODAY(),"⚠ Vence hoy",IF(D30-TODAY()<=5,"⚠ Vence en "&(D30-TODAY())&" día(s)","Pendiente"))))))) | G30: =IF(B30="","",SERVICIOS!R27)
B31: El «promedio» es lo que pagás en promedio por mes: sirve para estimar cuánto te falta pagar. Es una referencia, no el monto exacto de la factura.
B34: MIX SHOP DIGITAL · Herramientas inteligentes que simplifican tu vida.
B35: Versión gratuita · Más herramientas gratuitas para tu vida diaria → mixshopdigital.com.py

Sheet AJUSTES
C1: AJUSTES
B2: Herramientas inteligentes que simplifican tu vida. | C2: Cargalos una sola vez
B4: ← VOLVER | C4: Completá solamente las celdas amarillas. Estos datos alimentan las demás hojas automáticamente.
B6: 1. TU HOGAR
B7: Nombre del hogar | C7: Hogar de María (EJEMPLO) | D7: Aparece en el PANEL.
B8: Año a controlar | C8: 2026 | D8: El PANEL y SERVICIOS muestran los 12 meses de este año.
B9: Moneda | C9: Gs. | D9: Símbolo que se muestra en las hojas.
B10: Presupuesto mensual del hogar | C10: 4200000 | D10: Cuánto querés gastar como máximo por mes en estos servicios y gastos fijos. Si no tenés, dejalo en 0.
B12: 2. CATEGORÍAS (podés renombrarlas)
B13: Se usan en la lista desplegable de SERVICIOS. Cambiá el nombre, pero no dejes huecos entre medio.
B14: Servicios básicos | C14: Hasta 8 categorías.
B15: Comunicaciones
B16: Vivienda
B17: Educación
B18: Salud
B19: Seguros
B20: Transporte
B21: Otros
B25: MIX SHOP DIGITAL · Herramientas inteligentes que simplifican tu vida.
B26: Versión gratuita · Más herramientas gratuitas para tu vida diaria → mixshopdigital.com.py

Sheet AYUDA
D1: AYUDA
B2: Herramientas inteligentes que simplifican tu vida. | D2: Se aprende en 2 minutos
B4: ← VOLVER | C4: Leé esta hoja una vez. Después ya no la vas a necesitar.
B6: ¿PARA QUÉ SIRVE?
B7: Para tener a mano cuánto pagás de agua, luz, internet, cable y demás gastos fijos del hogar, mes por mes, y no olvidarte de ningún vencimiento. Sin fórmulas y sin Internet.
B9: EMPEZÁ EN 3 PASOS
B10: 1) En AJUSTES poné el nombre de tu hogar, el año y, si querés, tu presupuesto mensual.
B11: 2) En SERVICIOS revisá la lista (podés cambiar los nombres y agregar más), poné el día de vencimiento de cada uno y escribí cuánto pagaste cada mes.
B12: 3) Mirá el PANEL para ver tus gastos y VENCIMIENTOS para saber qué te falta pagar este mes.
B14: COLORES Y AVISOS
B15: Amarillo claro: celdas que completás vos. Gris o blanco: se calcula solo (bloqueado). Naranja en SERVICIOS: el monto subió más de 20 % respecto del mes anterior. En VENCIMIENTOS: verde pagado, naranja por vencer, rojo vencido.
B17: PREGUNTAS FRECUENTES
B18: • Veo todo en cero: hacé clic en «Habilitar edición» en la barra amarilla de Excel.
B19: • ¿Cómo marco un servicio como pagado? Escribí el monto pagado en la columna del mes. Mientras esté vacío, figura como pendiente.
B20: • ¿Cómo agrego un servicio? Escribí su nombre en una fila libre de SERVICIOS (hay 20 filas).
... B34: Versión gratuita · Más herramientas gratuitas para tu vida diaria → mixshopdigital.com.py
