Workbook
Name NombreNegocio: 'AJUSTES'!$C$7
Name AnioCtl: 'AJUSTES'!$C$8
Name Moneda: 'AJUSTES'!$C$9
Name Decimales: 'AJUSTES'!$C$10
Name TasaGeneral: 'AJUSTES'!$C$13
Name TasaReducida: 'AJUSTES'!$C$14
Name Arrastre: 'AJUSTES'!$C$18
Name SaldoIni: 'AJUSTES'!$C$19
Name MesN: 'RESUMEN'!$P$6
Name FIni: 'RESUMEN'!$P$7
Name FFin: 'RESUMEN'!$P$8

Sheet CALCULADORA
B1: MIX SHOP DIGITAL | F1: CALCULADORA DE IVA PARAGUAY
B2: Herramientas inteligentes que simplifican tu vida. | F2: Calculá el IVA en 3 pasos
C4: Completá las 3 celdas amarillas y mirá el resultado al instante. Para tu IVA del mes, usá REGISTRO y RESUMEN.
B5: + Registro de facturas | E5: Resumen | G5: Ajustes | I5: Ayuda
B7: 1. INGRESÁ EL MONTO
B9: Monto | D9: 1100000 | G9: Escribí el monto tal como figura en la factura o en tu lista de precios. Elegí si ya incluye el IVA y qué tasa corresponde. | P9: =IF($D$11="10 %",TasaGeneral,IF($D$11="5 %",TasaReducida,0))
B10: El monto… | D10: Con IVA incluido | P10: =IF(LEFT($D$10,3)="Con",1,0)
B11: Tasa de IVA | D11: 10 %
B13: PRECIO SIN IVA | E13: IVA | H13: TOTAL (CON IVA) | K13: TASA APLICADA
B14: =H14-E14 | E14: =IF(N(D9)=0,0,IF(P10=1,ROUND(D9*P9/(1+P9),Decimales),ROUND(D9*P9,Decimales))) | H14: =IF(N(D9)=0,0,IF(P10=1,D9,ROUND(D9*(1+P9),Decimales))) | K14: =IF(D11="","-",D11)
B15: =Moneda | E15: =Moneda | H15: =Moneda | K15: de IVA
B17: =IF(N(D9)=0,"Escribí un monto para calcular el IVA.","De "&FIXED(H14,Decimales)&" "&Moneda&" de total, "&FIXED(E14,Decimales)&" es IVA y "&FIXED(B14,Decimales)&" es el precio sin IVA.")
B19: 2. COMPARÁ LAS TASAS CON EL MISMO MONTO
B21: Tasa | D21: Precio sin IVA | E21: IVA | F21: Total
B22: Tasa 10 % | D22: =F22-E22 | E22: =IF(N($D$9)=0,0,IF($P$10=1,ROUND($D$9*$P22/(1+$P22),Decimales),ROUND($D$9*$P22,Decimales))) | F22: =IF(N($D$9)=0,0,IF($P$10=1,$D$9,ROUND($D$9*(1+$P22),Decimales))) | P22: =TasaGeneral
B23: Tasa 5 % | D23: =F23-E23 | E23: =IF(N($D$9)=0,0,IF($P$10=1,ROUND($D$9*$P23/(1+$P23),Decimales),ROUND($D$9*$P23,Decimales))) | F23: =IF(N($D$9)=0,0,IF($P$10=1,$D$9,ROUND($D$9*(1+$P23),Decimales))) | P23: =TasaReducida
B24: Exenta | D24: =F24-E24 | E24: =IF(N($D$9)=0,0,IF($P$10=1,ROUND($D$9*$P24/(1+$P24),Decimales),ROUND($D$9*$P24,Decimales))) | F24: =IF(N($D$9)=0,0,IF($P$10=1,$D$9,ROUND($D$9*(1+$P24),Decimales))) | P24: 0
B25: La fila resaltada es la tasa que elegiste.
B27: ¿CÓMO SE CALCULA?
B28: IVA 10 % incluido: IVA = total × 10 ÷ 110
B29: IVA 5 % incluido: IVA = total × 5 ÷ 105
B30: Precio sin IVA: IVA = precio × 10 % (o × 5 %)
B31: Exenta: no se suma IVA
B37: MIX SHOP DIGITAL · Herramientas inteligentes que simplifican tu vida.
B38: Versión gratuita · ¿Sos contador o llevás tus propios impuestos? Conocé ContadorPy Pro → mixshopdigital.com.py

Sheet REGISTRO
B1: MIX SHOP DIGITAL | E1: REGISTRO
B2: Herramientas inteligentes que simplifican tu vida. | E2: Anotá tus ventas y compras
B4: ← VOLVER | C4: Una fila por factura. Completá solamente las celdas amarillas: el IVA se calcula solo.
B5: ="Registros: "&COUNT(F7:F306)&" de 300 · IVA ventas del año: "&FIXED(RESUMEN!E29,Decimales)&" · IVA compras del año: "&FIXED(RESUMEN!F29,Decimales)&" "&Moneda&IF(SUMPRODUCT(--(F7:F306<>""),--((B7:B306="")+(C7:C306="")+(E7:E306="")>0))>0," · ⚠ Hay filas incompletas","")
B6: Fecha | C6: Tipo | D6: Detalle (opcional) | E6: Tasa de IVA | F6: Monto total (con IVA) | G6: Precio sin IVA | H6: IVA
B7: 46023 | C7: Venta | D7: Ejemplo: venta a cliente | E7: 10 % | F7: 1190000 | G7: =IF(H7="","",F7-H7) | H7: =IF(OR($F7="",$E7=""),"",IF($E7="10 %",ROUND($F7*TasaGeneral/(1+TasaGeneral),Decimales),IF($E7="5 %",ROUND($F7*TasaReducida/(1+TasaReducida),Decimales),0)))
B8: 46023 | C8: Venta | D8: Ejemplo: venta a cliente | E8: 10 % | F8: 1884000 | G8: =IF(H8="","",F8-H8) | H8: =IF(OR($F8="",$E8=""),"",IF($E8="10 %",ROUND($F8*TasaGeneral/(1+TasaGeneral),Decimales),IF($E8="5 %",ROUND($F8*TasaReducida/(1+TasaReducida),Decimales),0)))
B9: 46027 | C9: Venta | D9: Ejemplo: venta a cliente | E9: 10 % | F9: 2906000 | G9: =IF(H9="","",F9-H9) | H9: =IF(OR($F9="",$E9=""),"",IF($E9="10 %",ROUND($F9*TasaGeneral/(1+TasaGeneral),Decimales),IF($E9="5 %",ROUND($F9*TasaReducida/(1+TasaReducida),Decimales),0)))
B10: 46030 | C10: Venta | D10: Ejemplo: venta a cliente | E10: 10 % | F10: 2840000 | G10: =IF(H10="","",F10-H10) | H10: =IF(OR($F10="",$E10=""),"",IF($E10="10 %",ROUND($F10*TasaGeneral/(1+TasaGeneral),Decimales),IF($E10="5 %",ROUND($F10*TasaReducida/(1+TasaReducida),Decimales),0)))
B11: 46031 | C11: Venta | D11: Ejemplo: venta a cliente | E11: 10 % | F11: 2954000 | G11: =IF(H11="","",F11-H11) | H11: =IF(OR($F11="",$E11=""),"",IF($E11="10 %",ROUND($F11*TasaGeneral/(1+TasaGeneral),Decimales),IF($E11="5 %",ROUND($F11*TasaReducida/(1+TasaReducida),Decimales),0)))
B12: 46033 | C12: Compra | D12: Ejemplo: flete | E12: 10 % | F12: 1431000 | G12: =IF(H12="","",F12-H12) | H12: =IF(OR($F12="",$E12=""),"",IF($E12="10 %",ROUND($F12*TasaGeneral/(1+TasaGeneral),Decimales),IF($E12="5 %",ROUND($F12*TasaReducida/(1+TasaReducida),Decimales),0)))
B13: 46041 | C13: Compra | D13: Ejemplo: publicidad | E13: 5 % | F13: 1685000 | G13: =IF(H13="","",F13-H13) | H13: =IF(OR($F13="",$E13=""),"",IF($E13="10 %",ROUND($F13*TasaGeneral/(1+TasaGeneral),Decimales),IF($E13="5 %",ROUND($F13*TasaReducida/(1+TasaReducida),Decimales),0)))
B14: 46042 | C14: Compra | D14: Ejemplo: mercadería | E14: 10 % | F14: 1621000 | G14: =IF(H14="","",F14-H14) | H14: =IF(OR($F14="",$E14=""),"",IF($E14="10 %",ROUND($F14*TasaGeneral/(1+TasaGeneral),Decimales),IF($E14="5 %",ROUND($F14*TasaReducida/(1+TasaReducida),Decimales),0)))
B15: 46045 | C15: Venta | D15: Ejemplo: venta a cliente | E15: 10 % | F15: 2227000 | G15: =IF(H15="","",F15-H15) | H15: =IF(OR($F15="",$E15=""),"",IF($E15="10 %",ROUND($F15*TasaGeneral/(1+TasaGeneral),Decimales),IF($E15="5 %",ROUND($F15*TasaReducida/(1+TasaReducida),Decimales),0)))
B16: 46046 | C16: Compra | D16: Ejemplo: insumos | E16: 10 % | F16: 1128000 | G16: =IF(H16="","",F16-H16) | H16: =IF(OR($F16="",$E16=""),"",IF($E16="10 %",ROUND($F16*TasaGeneral/(1+TasaGeneral),Decimales),IF($E16="5 %",ROUND($F16*TasaReducida/(1+TasaReducida),Decimales),0)))
B17: 46047 | C17: Compra | D17: Ejemplo: servicios | E17: 10 % | F17: 732000 | G17: =IF(H17="","",F17-H17) | H17: =IF(OR($F17="",$E17=""),"",IF($E17="10 %",ROUND($F17*TasaGeneral/(1+TasaGeneral),Decimales),IF($E17="5 %",ROUND($F17*TasaReducida/(1+TasaReducida),Decimales),0)))
B18: 46057 | C18: Venta | D18: Ejemplo: venta a cliente | E18: 10 % | F18: 2263000 | G18: =IF(H18="","",F18-H18) | H18: =IF(OR($F18="",$E18=""),"",IF($E18="10 %",ROUND($F18*TasaGeneral/(1+TasaGeneral),Decimales),IF($E18="5 %",ROUND($F18*TasaReducida/(1+TasaReducida),Decimales),0)))
... B117: 46321 | C117: Compra | D117: Ejemplo: flete | E117: 5 % | F117: 2641000 | G117: =IF(H117="","",F117-H117) | H117: =IF(OR($F117="",$E117=""),"",IF($E117="10 %",ROUND($F117*TasaGeneral/(1+TasaGeneral),Decimales),IF($E117="5 %",ROUND($F117*TasaReducida/(1+TasaReducida),Decimales),0)))
G118: =IF(H118="","",F118-H118) | H118: =IF(OR($F118="",$E118=""),"",IF($E118="10 %",ROUND($F118*TasaGeneral/(1+TasaGeneral),Decimales),IF($E118="5 %",ROUND($F118*TasaReducida/(1+TasaReducida),Decimales),0)))
G119: =IF(H119="","",F119-H119) | H119: =IF(OR($F119="",$E119=""),"",IF($E119="10 %",ROUND($F119*TasaGeneral/(1+TasaGeneral),Decimales),IF($E119="5 %",ROUND($F119*TasaReducida/(1+TasaReducida),Decimales),0)))
G120: =IF(H120="","",F120-H120) | H120: =IF(OR($F120="",$E120=""),"",IF($E120="10 %",ROUND($F120*TasaGeneral/(1+TasaGeneral),Decimales),IF($E120="5 %",ROUND($F120*TasaReducida/(1+TasaReducida),Decimales),0)))
G121: =IF(H121="","",F121-H121) | H121: =IF(OR($F121="",$E121=""),"",IF($E121="10 %",ROUND($F121*TasaGeneral/(1+TasaGeneral),Decimales),IF($E121="5 %",ROUND($F121*TasaReducida/(1+TasaReducida),Decimales),0)))
G122: =IF(H122="","",F122-H122) | H122: =IF(OR($F122="",$E122=""),"",IF($E122="10 %",ROUND($F122*TasaGeneral/(1+TasaGeneral),Decimales),IF($E122="5 %",ROUND($F122*TasaReducida/(1+TasaReducida),Decimales),0)))
G123: =IF(H123="","",F123-H123) | H123: =IF(OR($F123="",$E123=""),"",IF($E123="10 %",ROUND($F123*TasaGeneral/(1+TasaGeneral),Decimales),IF($E123="5 %",ROUND($F123*TasaReducida/(1+TasaReducida),Decimales),0)))
G124: =IF(H124="","",F124-H124) | H124: =IF(OR($F124="",$E124=""),"",IF($E124="10 %",ROUND($F124*TasaGeneral/(1+TasaGeneral),Decimales),IF($E124="5 %",ROUND($F124*TasaReducida/(1+TasaReducida),Decimales),0)))
G125: =IF(H125="","",F125-H125) | H125: =IF(OR($F125="",$E125=""),"",IF($E125="10 %",ROUND($F125*TasaGeneral/(1+TasaGeneral),Decimales),IF($E125="5 %",ROUND($F125*TasaReducida/(1+TasaReducida),Decimales),0)))
G126: =IF(H126="","",F126-H126) | H126: =IF(OR($F126="",$E126=""),"",IF($E126="10 %",ROUND($F126*TasaGeneral/(1+TasaGeneral),Decimales),IF($E126="5 %",ROUND($F126*TasaReducida/(1+TasaReducida),Decimales),0)))
G127: =IF(H127="","",F127-H127) | H127: =IF(OR($F127="",$E127=""),"",IF($E127="10 %",ROUND($F127*TasaGeneral/(1+TasaGeneral),Decimales),IF($E127="5 %",ROUND($F127*TasaReducida/(1+TasaReducida),Decimales),0)))
G128: =IF(H128="","",F128-H128) | H128: =IF(OR($F128="",$E128=""),"",IF($E128="10 %",ROUND($F128*TasaGeneral/(1+TasaGeneral),Decimales),IF($E128="5 %",ROUND($F128*TasaReducida/(1+TasaReducida),Decimales),0)))
G129: =IF(H129="","",F129-H129) | H129: =IF(OR($F129="",$E129=""),"",IF($E129="10 %",ROUND($F129*TasaGeneral/(1+TasaGeneral),Decimales),IF($E129="5 %",ROUND($F129*TasaReducida/(1+TasaReducida),Decimales),0)))
... G306: =IF(H306="","",F306-H306) | H306: =IF(OR($F306="",$E306=""),"",IF($E306="10 %",ROUND($F306*TasaGeneral/(1+TasaGeneral),Decimales),IF($E306="5 %",ROUND($F306*TasaReducida/(1+TasaReducida),Decimales),0)))
B309: MIX SHOP DIGITAL · Herramientas inteligentes que simplifican tu vida.
B310: Versión gratuita · ¿Sos contador o llevás tus propios impuestos? Conocé ContadorPy Pro → mixshopdigital.com.py

Sheet RESUMEN
B1: MIX SHOP DIGITAL | F1: RESUMEN DE IVA
B2: Herramientas inteligentes que simplifican tu vida. | F2: Tu IVA, mes a mes
B4: ← VOLVER | C4: El resumen se arma solo con lo que anotás en REGISTRO. No hace falta escribir nada acá, salvo elegir el período.
B5: Calculadora | E5: + Registro | G5: Ajustes | I5: Ayuda
B6: Período a mirar: | C6: Todo el año | E6: ="Año de control: "&AnioCtl&" · "&NombreNegocio | P6: =IFERROR(MATCH(C6,{"Todo el año","Enero","Febrero","Marzo","Abril","Mayo","Junio","Julio","Agosto","Septiembre","Octubre","Noviembre","Diciembre"},0)-1,0)
P7: =IF(P6=0,DATE(AnioCtl,1,1),DATE(AnioCtl,P6,1))
B8: IVA DÉBITO (cobrado en ventas) | E8: IVA CRÉDITO (pagado en compras) | H8: IVA A PAGAR | K8: SALDO A FAVOR | P8: =IF(P6=0,DATE(AnioCtl+1,1,1),DATE(AnioCtl,P6+1,1))
B9: =IF(MesN=0,E29,INDEX(E17:E28,MesN)) | E9: =IF(MesN=0,F29,INDEX(F17:F28,MesN)) | H9: =IF(MesN=0,H29,INDEX(H17:H28,MesN)) | K9: =IF(MesN=0,I28,INDEX(I17:I28,MesN))
B10: =Moneda | E10: =Moneda | H10: débito − crédito | K10: para el mes siguiente
B12: =IF(AND(B9=0,E9=0),"Anotá tus primeras ventas y compras en la hoja REGISTRO para ver tu IVA.",IF(H9>0,"⚠ IVA a pagar en este período: "&FIXED(H9,Decimales)&" "&Moneda&" — recordá presentar y pagar a tiempo.",IF(K9>0,"✔ Tenés saldo a favor de "&FIXED(K9,Decimales)&" "&Moneda&" para los próximos meses.","✔ Tu IVA de este período está en cero.")))
B15: MES A MES | J15: DATOS CLAVE DEL AÑO
B16: Mes | C16: Ventas (con IVA) | D16: Compras (con IVA) | E16: IVA débito | F16: IVA crédito | G16: Saldo a favor anterior | H16: IVA a pagar | I16: Saldo a favor
B17: Enero | C17: =SUMIFS(REGISTRO!$F$7:$F$306,REGISTRO!$C$7:$C$306,"Venta",REGISTRO!$B$7:$B$306,">="&DATE(AnioCtl,1,1),REGISTRO!$B$7:$B$306,"<"&DATE(AnioCtl,2,1)) | D17: =SUMIFS(REGISTRO!$F$7:$F$306,REGISTRO!$C$7:$C$306,"Compra",REGISTRO!$B$7:$B$306,">="&DATE(AnioCtl,1,1),REGISTRO!$B$7:$B$306,"<"&DATE(AnioCtl,2,1)) | E17: =SUMIFS(REGISTRO!$H$7:$H$306,REGISTRO!$C$7:$C$306,"Venta",REGISTRO!$B$7:$B$306,">="&DATE(AnioCtl,1,1),REGISTRO!$B$7:$B$306,"<"&DATE(AnioCtl,2,1)) | F17: =SUMIFS(REGISTRO!$H$7:$H$306,REGISTRO!$C$7:$C$306,"Compra",REGISTRO!$B$7:$B$306,">="&DATE(AnioCtl,1,1),REGISTRO!$B$7:$B$306,"<"&DATE(AnioCtl,2,1)) | G17: =IF(Arrastre="Sí",SaldoIni,0) | H17: =MAX(0,E17-F17-G17) | I17: =MAX(0,F17+G17-E17) | J17: IVA a pagar en el año
B18: Febrero | C18: =SUMIFS(REGISTRO!$F$7:$F$306,REGISTRO!$C$7:$C$306,"Venta",REGISTRO!$B$7:$B$306,">="&DATE(AnioCtl,2,1),REGISTRO!$B$7:$B$306,"<"&DATE(AnioCtl,3,1)) | D18: =SUMIFS(REGISTRO!$F$7:$F$306,REGISTRO!$C$7:$C$306,"Compra",REGISTRO!$B$7:$B$306,">="&DATE(AnioCtl,2,1),REGISTRO!$B$7:$B$306,"<"&DATE(AnioCtl,3,1)) | E18: =SUMIFS(REGISTRO!$H$7:$H$306,REGISTRO!$C$7:$C$306,"Venta",REGISTRO!$B$7:$B$306,">="&DATE(AnioCtl,2,1),REGISTRO!$B$7:$B$306,"<"&DATE(AnioCtl,3,1)) | F18: =SUMIFS(REGISTRO!$H$7:$H$306,REGISTRO!$C$7:$C$306,"Compra",REGISTRO!$B$7:$B$306,">="&DATE(AnioCtl,2,1),REGISTRO!$B$7:$B$306,"<"&DATE(AnioCtl,3,1)) | G18: =IF(Arrastre="Sí",I17,0) | H18: =MAX(0,E18-F18-G18) | I18: =MAX(0,F18+G18-E18) | J18: =H29
B19: Marzo | C19: =SUMIFS(REGISTRO!$F$7:$F$306,REGISTRO!$C$7:$C$306,"Venta",REGISTRO!$B$7:$B$306,">="&DATE(AnioCtl,3,1),REGISTRO!$B$7:$B$306,"<"&DATE(AnioCtl,4,1)) | D19: =SUMIFS(REGISTRO!$F$7:$F$306,REGISTRO!$C$7:$C$306,"Compra",REGISTRO!$B$7:$B$306,">="&DATE(AnioCtl,3,1),REGISTRO!$B$7:$B$306,"<"&DATE(AnioCtl,4,1)) | E19: =SUMIFS(REGISTRO!$H$7:$H$306,REGISTRO!$C$7:$C$306,"Venta",REGISTRO!$B$7:$B$306,">="&DATE(AnioCtl,3,1),REGISTRO!$B$7:$B$306,"<"&DATE(AnioCtl,4,1)) | F19: =SUMIFS(REGISTRO!$H$7:$H$306,REGISTRO!$C$7:$C$306,"Compra",REGISTRO!$B$7:$B$306,">="&DATE(AnioCtl,3,1),REGISTRO!$B$7:$B$306,"<"&DATE(AnioCtl,4,1)) | G19: =IF(Arrastre="Sí",I18,0) | H19: =MAX(0,E19-F19-G19) | I19: =MAX(0,F19+G19-E19) | J19: Saldo a favor al cierre
B20: Abril | C20: =SUMIFS(REGISTRO!$F$7:$F$306,REGISTRO!$C$7:$C$306,"Venta",REGISTRO!$B$7:$B$306,">="&DATE(AnioCtl,4,1),REGISTRO!$B$7:$B$306,"<"&DATE(AnioCtl,5,1)) | D20: =SUMIFS(REGISTRO!$F$7:$F$306,REGISTRO!$C$7:$C$306,"Compra",REGISTRO!$B$7:$B$306,">="&DATE(AnioCtl,4,1),REGISTRO!$B$7:$B$306,"<"&DATE(AnioCtl,5,1)) | E20: =SUMIFS(REGISTRO!$H$7:$H$306,REGISTRO!$C$7:$C$306,"Venta",REGISTRO!$B$7:$B$306,">="&DATE(AnioCtl,4,1),REGISTRO!$B$7:$B$306,"<"&DATE(AnioCtl,5,1)) | F20: =SUMIFS(REGISTRO!$H$7:$H$306,REGISTRO!$C$7:$C$306,"Compra",REGISTRO!$B$7:$B$306,">="&DATE(AnioCtl,4,1),REGISTRO!$B$7:$B$306,"<"&DATE(AnioCtl,5,1)) | G20: =IF(Arrastre="Sí",I19,0) | H20: =MAX(0,E20-F20-G20) | I20: =MAX(0,F20+G20-E20) | J20: =I28
B21: Mayo | C21: =SUMIFS(REGISTRO!$F$7:$F$306,REGISTRO!$C$7:$C$306,"Venta",REGISTRO!$B$7:$B$306,">="&DATE(AnioCtl,5,1),REGISTRO!$B$7:$B$306,"<"&DATE(AnioCtl,6,1)) | D21: =SUMIFS(REGISTRO!$F$7:$F$306,REGISTRO!$C$7:$C$306,"Compra",REGISTRO!$B$7:$B$306,">="&DATE(AnioCtl,5,1),REGISTRO!$B$7:$B$306,"<"&DATE(AnioCtl,6,1)) | E21: =SUMIFS(REGISTRO!$H$7:$H$306,REGISTRO!$C$7:$C$306,"Venta",REGISTRO!$B$7:$B$306,">="&DATE(AnioCtl,5,1),REGISTRO!$B$7:$B$306,"<"&DATE(AnioCtl,6,1)) | F21: =SUMIFS(REGISTRO!$H$7:$H$306,REGISTRO!$C$7:$C$306,"Compra",REGISTRO!$B$7:$B$306,">="&DATE(AnioCtl,5,1),REGISTRO!$B$7:$B$306,"<"&DATE(AnioCtl,6,1)) | G21: =IF(Arrastre="Sí",I20,0) | H21: =MAX(0,E21-F21-G21) | I21: =MAX(0,F21+G21-E21) | J21: Mes con más IVA a pagar
B22: Junio | C22: =SUMIFS(REGISTRO!$F$7:$F$306,REGISTRO!$C$7:$C$306,"Venta",REGISTRO!$B$7:$B$306,">="&DATE(AnioCtl,6,1),REGISTRO!$B$7:$B$306,"<"&DATE(AnioCtl,7,1)) | D22: =SUMIFS(REGISTRO!$F$7:$F$306,REGISTRO!$C$7:$C$306,"Compra",REGISTRO!$B$7:$B$306,">="&DATE(AnioCtl,6,1),REGISTRO!$B$7:$B$306,"<"&DATE(AnioCtl,7,1)) | E22: =SUMIFS(REGISTRO!$H$7:$H$306,REGISTRO!$C$7:$C$306,"Venta",REGISTRO!$B$7:$B$306,">="&DATE(AnioCtl,6,1),REGISTRO!$B$7:$B$306,"<"&DATE(AnioCtl,7,1)) | F22: =SUMIFS(REGISTRO!$H$7:$H$306,REGISTRO!$C$7:$C$306,"Compra",REGISTRO!$B$7:$B$306,">="&DATE(AnioCtl,6,1),REGISTRO!$B$7:$B$306,"<"&DATE(AnioCtl,7,1)) | G22: =IF(Arrastre="Sí",I21,0) | H22: =MAX(0,E22-F22-G22) | I22: =MAX(0,F22+G22-E22) | J22: =IF(MAX(H17:H28)<=0,"-",INDEX(B17:B28,MATCH(MAX(H17:H28),H17:H28,0)))
B23: Julio | C23: =SUMIFS(REGISTRO!$F$7:$F$306,REGISTRO!$C$7:$C$306,"Venta",REGISTRO!$B$7:$B$306,">="&DATE(AnioCtl,7,1),REGISTRO!$B$7:$B$306,"<"&DATE(AnioCtl,8,1)) | D23: =SUMIFS(REGISTRO!$F$7:$F$306,REGISTRO!$C$7:$C$306,"Compra",REGISTRO!$B$7:$B$306,">="&DATE(AnioCtl,7,1),REGISTRO!$B$7:$B$306,"<"&DATE(AnioCtl,8,1)) | E23: =SUMIFS(REGISTRO!$H$7:$H$306,REGISTRO!$C$7:$C$306,"Venta",REGISTRO!$B$7:$B$306,">="&DATE(AnioCtl,7,1),REGISTRO!$B$7:$B$306,"<"&DATE(AnioCtl,8,1)) | F23: =SUMIFS(REGISTRO!$H$7:$H$306,REGISTRO!$C$7:$C$306,"Compra",REGISTRO!$B$7:$B$306,">="&DATE(AnioCtl,7,1),REGISTRO!$B$7:$B$306,"<"&DATE(AnioCtl,8,1)) | G23: =IF(Arrastre="Sí",I22,0) | H23: =MAX(0,E23-F23-G23) | I23: =MAX(0,F23+G23-E23) | J23: Meses con saldo a favor
B24: Agosto | C24: =SUMIFS(REGISTRO!$F$7:$F$306,REGISTRO!$C$7:$C$306,"Venta",REGISTRO!$B$7:$B$306,">="&DATE(AnioCtl,8,1),REGISTRO!$B$7:$B$306,"<"&DATE(AnioCtl,9,1)) | D24: =SUMIFS(REGISTRO!$F$7:$F$306,REGISTRO!$C$7:$C$306,"Compra",REGISTRO!$B$7:$B$306,">="&DATE(AnioCtl,8,1),REGISTRO!$B$7:$B$306,"<"&DATE(AnioCtl,9,1)) | E24: =SUMIFS(REGISTRO!$H$7:$H$306,REGISTRO!$C$7:$C$306,"Venta",REGISTRO!$B$7:$B$306,">="&DATE(AnioCtl,8,1),REGISTRO!$B$7:$B$306,"<"&DATE(AnioCtl,9,1)) | F24: =SUMIFS(REGISTRO!$H$7:$H$306,REGISTRO!$C$7:$C$306,"Compra",REGISTRO!$B$7:$B$306,">="&DATE(AnioCtl,8,1),REGISTRO!$B$7:$B$306,"<"&DATE(AnioCtl,9,1)) | G24: =IF(Arrastre="Sí",I23,0) | H24: =MAX(0,E24-F24-G24) | I24: =MAX(0,F24+G24-E24) | J24: =COUNTIF(I17:I28,">0")
B25: Septiembre | C25: =SUMIFS(REGISTRO!$F$7:$F$306,REGISTRO!$C$7:$C$306,"Venta",REGISTRO!$B$7:$B$306,">="&DATE(AnioCtl,9,1),REGISTRO!$B$7:$B$306,"<"&DATE(AnioCtl,10,1)) | D25: =SUMIFS(REGISTRO!$F$7:$F$306,REGISTRO!$C$7:$C$306,"Compra",REGISTRO!$B$7:$B$306,">="&DATE(AnioCtl,9,1),REGISTRO!$B$7:$B$306,"<"&DATE(AnioCtl,10,1)) | E25: =SUMIFS(REGISTRO!$H$7:$H$306,REGISTRO!$C$7:$C$306,"Venta",REGISTRO!$B$7:$B$306,">="&DATE(AnioCtl,9,1),REGISTRO!$B$7:$B$306,"<"&DATE(AnioCtl,10,1)) | F25: =SUMIFS(REGISTRO!$H$7:$H$306,REGISTRO!$C$7:$C$306,"Compra",REGISTRO!$B$7:$B$306,">="&DATE(AnioCtl,9,1),REGISTRO!$B$7:$B$306,"<"&DATE(AnioCtl,10,1)) | G25: =IF(Arrastre="Sí",I24,0) | H25: =MAX(0,E25-F25-G25) | I25: =MAX(0,F25+G25-E25) | J25: IVA a pagar sobre ventas
B26: Octubre | C26: =SUMIFS(REGISTRO!$F$7:$F$306,REGISTRO!$C$7:$C$306,"Venta",REGISTRO!$B$7:$B$306,">="&DATE(AnioCtl,10,1),REGISTRO!$B$7:$B$306,"<"&DATE(AnioCtl,11,1)) | D26: =SUMIFS(REGISTRO!$F$7:$F$306,REGISTRO!$C$7:$C$306,"Compra",REGISTRO!$B$7:$B$306,">="&DATE(AnioCtl,10,1),REGISTRO!$B$7:$B$306,"<"&DATE(AnioCtl,11,1)) | E26: =SUMIFS(REGISTRO!$H$7:$H$306,REGISTRO!$C$7:$C$306,"Venta",REGISTRO!$B$7:$B$306,">="&DATE(AnioCtl,10,1),REGISTRO!$B$7:$B$306,"<"&DATE(AnioCtl,11,1)) | F26: =SUMIFS(REGISTRO!$H$7:$H$306,REGISTRO!$C$7:$C$306,"Compra",REGISTRO!$B$7:$B$306,">="&DATE(AnioCtl,10,1),REGISTRO!$B$7:$B$306,"<"&DATE(AnioCtl,11,1)) | G26: =IF(Arrastre="Sí",I25,0) | H26: =MAX(0,E26-F26-G26) | I26: =MAX(0,F26+G26-E26) | J26: =IF(C29=0,0,H29/C29)
B27: Noviembre | C27: =SUMIFS(REGISTRO!$F$7:$F$306,REGISTRO!$C$7:$C$306,"Venta",REGISTRO!$B$7:$B$306,">="&DATE(AnioCtl,11,1),REGISTRO!$B$7:$B$306,"<"&DATE(AnioCtl,12,1)) | D27: =SUMIFS(REGISTRO!$F$7:$F$306,REGISTRO!$C$7:$C$306,"Compra",REGISTRO!$B$7:$B$306,">="&DATE(AnioCtl,11,1),REGISTRO!$B$7:$B$306,"<"&DATE(AnioCtl,12,1)) | E27: =SUMIFS(REGISTRO!$H$7:$H$306,REGISTRO!$C$7:$C$306,"Venta",REGISTRO!$B$7:$B$306,">="&DATE(AnioCtl,11,1),REGISTRO!$B$7:$B$306,"<"&DATE(AnioCtl,12,1)) | F27: =SUMIFS(REGISTRO!$H$7:$H$306,REGISTRO!$C$7:$C$306,"Compra",REGISTRO!$B$7:$B$306,">="&DATE(AnioCtl,11,1),REGISTRO!$B$7:$B$306,"<"&DATE(AnioCtl,12,1)) | G27: =IF(Arrastre="Sí",I26,0) | H27: =MAX(0,E27-F27-G27) | I27: =MAX(0,F27+G27-E27)
B28: Diciembre | C28: =SUMIFS(REGISTRO!$F$7:$F$306,REGISTRO!$C$7:$C$306,"Venta",REGISTRO!$B$7:$B$306,">="&DATE(AnioCtl,12,1),REGISTRO!$B$7:$B$306,"<"&DATE(AnioCtl,13,1)) | D28: =SUMIFS(REGISTRO!$F$7:$F$306,REGISTRO!$C$7:$C$306,"Compra",REGISTRO!$B$7:$B$306,">="&DATE(AnioCtl,12,1),REGISTRO!$B$7:$B$306,"<"&DATE(AnioCtl,13,1)) | E28: =SUMIFS(REGISTRO!$H$7:$H$306,REGISTRO!$C$7:$C$306,"Venta",REGISTRO!$B$7:$B$306,">="&DATE(AnioCtl,12,1),REGISTRO!$B$7:$B$306,"<"&DATE(AnioCtl,13,1)) | F28: =SUMIFS(REGISTRO!$H$7:$H$306,REGISTRO!$C$7:$C$306,"Compra",REGISTRO!$B$7:$B$306,">="&DATE(AnioCtl,12,1),REGISTRO!$B$7:$B$306,"<"&DATE(AnioCtl,13,1)) | G28: =IF(Arrastre="Sí",I27,0) | H28: =MAX(0,E28-F28-G28) | I28: =MAX(0,F28+G28-E28)
B29: TOTAL | C29: =SUM(C17:C28) | D29: =SUM(D17:D28) | E29: =SUM(E17:E28) | F29: =SUM(F17:F28) | H29: =SUM(H17:H28) | I29: =I28
B31: GRÁFICOS
B50: VENTAS Y COMPRAS SEGÚN TASA (período elegido) | I50: Esta planilla ofrece una estimación orientativa del IVA. No reemplaza la liquidación oficial: confirmá tus números con tu contador antes de presentar tu declaración. Si querés llevar toda la contabilidad de forma profesional, conocé ContadorPy Pro.
B51: Tasa | D51: Ventas (con IVA) | E51: IVA débito | F51: Compras (con IVA) | G51: IVA crédito
B52: Tasa 10 % | D52: =SUMIFS(REGISTRO!$F$7:$F$306,REGISTRO!$C$7:$C$306,"Venta",REGISTRO!$E$7:$E$306,"10 %",REGISTRO!$B$7:$B$306,">="&FIni,REGISTRO!$B$7:$B$306,"<"&FFin) | E52: =SUMIFS(REGISTRO!$H$7:$H$306,REGISTRO!$C$7:$C$306,"Venta",REGISTRO!$E$7:$E$306,"10 %",REGISTRO!$B$7:$B$306,">="&FIni,REGISTRO!$B$7:$B$306,"<"&FFin) | F52: =SUMIFS(REGISTRO!$F$7:$F$306,REGISTRO!$C$7:$C$306,"Compra",REGISTRO!$E$7:$E$306,"10 %",REGISTRO!$B$7:$B$306,">="&FIni,REGISTRO!$B$7:$B$306,"<"&FFin) | G52: =SUMIFS(REGISTRO!$H$7:$H$306,REGISTRO!$C$7:$C$306,"Compra",REGISTRO!$E$7:$E$306,"10 %",REGISTRO!$B$7:$B$306,">="&FIni,REGISTRO!$B$7:$B$306,"<"&FFin)
B53: Tasa 5 % | D53: =SUMIFS(REGISTRO!$F$7:$F$306,REGISTRO!$C$7:$C$306,"Venta",REGISTRO!$E$7:$E$306,"5 %",REGISTRO!$B$7:$B$306,">="&FIni,REGISTRO!$B$7:$B$306,"<"&FFin) | E53: =SUMIFS(REGISTRO!$H$7:$H$306,REGISTRO!$C$7:$C$306,"Venta",REGISTRO!$E$7:$E$306,"5 %",REGISTRO!$B$7:$B$306,">="&FIni,REGISTRO!$B$7:$B$306,"<"&FFin) | F53: =SUMIFS(REGISTRO!$F$7:$F$306,REGISTRO!$C$7:$C$306,"Compra",REGISTRO!$E$7:$E$306,"5 %",REGISTRO!$B$7:$B$306,">="&FIni,REGISTRO!$B$7:$B$306,"<"&FFin) | G53: =SUMIFS(REGISTRO!$H$7:$H$306,REGISTRO!$C$7:$C$306,"Compra",REGISTRO!$E$7:$E$306,"5 %",REGISTRO!$B$7:$B$306,">="&FIni,REGISTRO!$B$7:$B$306,"<"&FFin)
B54: Exenta | D54: =SUMIFS(REGISTRO!$F$7:$F$306,REGISTRO!$C$7:$C$306,"Venta",REGISTRO!$E$7:$E$306,"Exenta",REGISTRO!$B$7:$B$306,">="&FIni,REGISTRO!$B$7:$B$306,"<"&FFin) | E54: =SUMIFS(REGISTRO!$H$7:$H$306,REGISTRO!$C$7:$C$306,"Venta",REGISTRO!$E$7:$E$306,"Exenta",REGISTRO!$B$7:$B$306,">="&FIni,REGISTRO!$B$7:$B$306,"<"&FFin) | F54: =SUMIFS(REGISTRO!$F$7:$F$306,REGISTRO!$C$7:$C$306,"Compra",REGISTRO!$E$7:$E$306,"Exenta",REGISTRO!$B$7:$B$306,">="&FIni,REGISTRO!$B$7:$B$306,"<"&FFin) | G54: =SUMIFS(REGISTRO!$H$7:$H$306,REGISTRO!$C$7:$C$306,"Compra",REGISTRO!$E$7:$E$306,"Exenta",REGISTRO!$B$7:$B$306,">="&FIni,REGISTRO!$B$7:$B$306,"<"&FFin)
B55: TOTAL | D55: =SUM(D52:D54) | E55: =SUM(E52:E54) | F55: =SUM(F52:F54) | G55: =SUM(G52:G54)
B59: MIX SHOP DIGITAL · Herramientas inteligentes que simplifican tu vida.
B60: Versión gratuita · ¿Sos contador o llevás tus propios impuestos? Conocé ContadorPy Pro → mixshopdigital.com.py

Sheet AJUSTES
B1: MIX SHOP DIGITAL | C1: AJUSTES
B2: Herramientas inteligentes que simplifican tu vida. | C2: Cargalos una sola vez
B4: ← VOLVER | C4: Completá solamente las celdas amarillas. Estos datos alimentan las demás hojas automáticamente.
B6: 1. TUS DATOS
B7: Nombre del negocio o contribuyente | C7: Tienda de María (EJEMPLO) | D7: Aparece en el RESUMEN.
B8: Año a controlar | C8: 2026 | D8: El RESUMEN muestra los 12 meses de este año. Los registros de otros años se ignoran.
B9: Moneda | C9: Gs. | D9: Símbolo que se muestra en las hojas.
B10: Decimales (automático) | C10: =IF(Moneda="Gs.",0,2) | D10: El guaraní no usa decimales; otras monedas usan 2.
B12: 2. TASAS DE IVA (fijadas por ley)
B13: Tasa general | C13: 0.1 | D13: 10 % — Ley 125/91, modificada por la Ley 6380/2019.
B14: Tasa reducida | C14: 0.05 | D14: 5 % — productos y servicios con tasa reducida.
B15: Las operaciones exentas no pagan IVA. Si la ley cambia, usá la versión actualizada de esta planilla.
B17: 3. SALDO A FAVOR
B18: ¿Arrastrar el saldo a favor? | C18: Sí | D18: Si en un mes pagaste más IVA en compras que el cobrado en ventas, ese saldo se descuenta del mes siguiente. Confirmalo con tu contador.
B19: Saldo a favor al iniciar el año | C19: 0 | D19: Solo si venís con saldo a favor de diciembre del año anterior. Si no, dejalo en 0.
B23: MIX SHOP DIGITAL · Herramientas inteligentes que simplifican tu vida.
B24: Versión gratuita · ¿Sos contador o llevás tus propios impuestos? Conocé ContadorPy Pro → mixshopdigital.com.py

Sheet AYUDA
B1: MIX SHOP DIGITAL | D1: AYUDA
B2: Herramientas inteligentes que simplifican tu vida. | D2: Se aprende en 2 minutos
B4: ← VOLVER | C4: Leé esta hoja una vez. Después ya no la vas a necesitar.
B6: ¿PARA QUÉ SIRVE?
B7: Para calcular el IVA de un precio al instante (10 %, 5 % o exenta) y para estimar cuánto IVA te toca pagar cada mes, a partir de tus facturas de ventas y de compras. Sin fórmulas y sin Internet.
B9: CALCULADORA
B10: Escribí el monto, elegí si ya incluye el IVA y elegí la tasa. Al instante ves el precio sin IVA, el IVA y el total. Abajo se comparan las tres tasas con el mismo monto.
B12: IVA MENSUAL EN 3 PASOS
B13: 1) En AJUSTES poné el nombre de tu negocio y el año que querés controlar.
B14: 2) En REGISTRO anotá cada factura: fecha, tipo (Venta o Compra), tasa de IVA y monto total. El IVA se calcula solo.
B15: 3) Mirá el RESUMEN: IVA débito (el que cobraste), IVA crédito (el que pagaste en tus compras) y el IVA a pagar de cada mes.
B17: COLORES
B18: Amarillo/lila claro: celdas que completás vos. Gris o blanco: se calcula solo (bloqueado). Violeta: ventas. Dorado: compras. Rosa: IVA a pagar.
B20: PREGUNTAS FRECUENTES
B21: • Veo todo en cero: hacé clic en «Habilitar edición» en la barra amarilla de Excel.
... B38: Versión gratuita · ¿Sos contador o llevás tus propios impuestos? Conocé ContadorPy Pro → mixshopdigital.com.py
